[
    {
        "title": "2025-1학기 교내장학금 신청안내(다문화, 장애인자녀, 장애대학생, 특수환경지원 장학금)",
        "url": "https://www.jj.ac.kr/jj/community/notice/janghaknotice.jsp?mode=view&article_no=446248&amp;board_wrapper=%2Fjj%2Fcommunity%2Fnotice%2Fjanghaknotice.jsp&amp;pager.offset=0&amp;board_no=1077",
        "content": "2025-1\n학기 교내장학금을 지급하고자 하오니 신입생 및 재학생은 다음 내용 확인 후 장학금 신청 바랍니다.\n1. 신청장학금: 교내장학금(다문화, 장애인자녀, 장애대학생, 특수환경지원)\n2. 신청기한: 2025. 1. 27.(월) ~ 2025. 2. 11.(화) 16:00\n3. 접 수 처: 학생회관 226호(학생지원실) 또는 e-mail(breeze@jj.ac.kr)\n4. 제출서류\n장학명\n장학금액\n자격요건\n제출서류\n다문화\n장학금\n50만원\n가. 다문화 가정의 이주민(결혼이민자) 혹은 다문화 가정의 자녀\n나. 직전학기 취득학점 12학점 이상, 평점평균 2.0 이상\n가.가족관계증명서\n나.외국인등록증,혼인관계증명서 등\n※ 국적 확인이 가능한 서류제출\n장애인자녀\n장학금\n수업료 50%\n가. 부·모의 장애 정도가 \"정도가 심한 장애인”인 경우\n나. 직전학기 취득학점12학점 이상, 평점평균 2.5 이상\n가.장학금 신청서(붙임문서 참조)\n나.가족관계증명서\n다.장애인증명서(부 또는 모)\n장애대학생\n장학금\n- 장애정도가 심한\n장애인: 200만원\n- 장애정도가 심하지\n않은 장애인: 50만원\n가. 직전학기 취득학점 관계 없음, 평점평균 2.0 이상\n가.장학금 신청서(붙임문서 참조)\n나.장애인증명서(본인)\n특수환경지원\n장학금\n- 수업료 60% 및 학업장려금 50만원\n유형 1: 아동복지시설에서 재원한 사실이 있는 자\n유형 2: 부모가 모두 사망하였거나 가출•행방불명인 자\n유형 3: 한부모가정의 부 또는 모가 교도소 수감 중인 자\n직전학기 취득학점 12학점 이상, 평점평균 2.0 이상\n가. 주민등록등본\n나. 유형별 해당 증빙서류\n5. 기타 유의사항\n가.\n신규자에 한하여 신청\n(\n입학 후\n1\n회 신청하면 매 학기 지급\n)\n나. 최종 선정자는 수업료 범위 내에서 고지서 선 감면 지급하며, 국가장학금 등의 중복지급으로 인해 장학금액 전액을 수혜받지 못하는\n경우가 발생 할 수 있음\n다. 신청자 중 장학금 지급 부적격 사유가 있는 자는 지급 불가함\n※ 문의: 063-220-2167\n붙임  장애인자녀 및 장애대학생 장학금 신청서 1\n부 ['이미지 없음']"
    },
    {
        "title": "주거안정장학금 신청(2/4 화~3/18 화) 안내",
        "url": "https://www.jj.ac.kr/jj/community/notice/janghaknotice.jsp?mode=view&article_no=446194&amp;board_wrapper=%2Fjj%2Fcommunity%2Fnotice%2Fjanghaknotice.jsp&amp;pager.offset=0&amp;board_no=1077",
        "content": "2025학년도부터 신설된 국가장학금(주거안정장학금) 신청기간을 안내하오니,\n원거리\n대학에 다니는\n기초/차상위학생\n은 신청 바랍니다.\n(신청방법은 첨부된 파일 참고!!) [\" \\n\\n25. 2. 4. (화) 9시 ~ 3. 18. (화) 18시\\n\\n \\n   \\n   \\n\\n \\n\\nAVSHS\\n원거리 대학에 다니는 기초:차상위학생(단.사입잠여대학에 한함)\\n\\n대학소재지 기준 부모님의 주소지가\\n\\n다른 교통권에 있는 경우\\n\\n#대도시권역 : 수도권 / 부산 ㆍ울산권 / 대구권 / 광주권 / 대젼권\\n{지역 : 인접(시외 경계를 맞당고 있는:시까지\\n\\nCBN Hest BAS ATA\\n\\n※상세 범위는 한국장학재단 누리집 참고\\n\\n \\n  \\n\\n솜 지원금액\\n\\n학기 중최대 월 20만원한도내\\n\\nAss\\n\\n학생이 제줄한주거안정장학금 지급 요청서 검토 후\\n\\n월 지급 한도 내에서 학생이 지출한 비용(실비)을 개별 지급\\n(학제별, 학생별 한도 내)\\n\\nft MEAS BGS! Siz\\n\\n'25. 2. 4.(화) 9시 ~ 3. 25. (Sh) 184]\\n\\n(2 서류제출 대상자는 온라인으로 서류제출 필수!\\n\\n6) 23부\\n\\n주거안점잠학금이란?\\n원거리 대학에 다니는\\n기초-차상위학생에게\\n\\n[주거관련 비용]을 지원하는 장학금\\n\\n※ 반드시 기간 내 신정\\n\\n   \\n  \\n\\nff Algor\\nLoon\\n\\nSta ashict Sele] Bt aupeletolal AV\\n*빈드시 학샘 본인이 시점 신정\\n\\n \\n\\n \\n\\n \\n\\n \\n\\n \\n\\n \\n\\n \\n\\n- 누리집                www, konaf.go.kr\\n한국장학재단   글           안정\\n콕잠학재단 장학금신정 } 신정서작성 + OES\\n+ SURRY\\nAndroid     106 '\\neae >) BB BISA > BENS\\n\\nff HAZ}\\n한국장화재탄\\n삼담센터\\n\\n1599-2000\\n\\x0c\"]"
    },
    {
        "title": "2025-1학기 국가장학금 2차 신청기간(2/4 화~3/18 화) 안내",
        "url": "https://www.jj.ac.kr/jj/community/notice/janghaknotice.jsp?mode=view&article_no=446176&amp;board_wrapper=%2Fjj%2Fcommunity%2Fnotice%2Fjanghaknotice.jsp&amp;pager.offset=0&amp;board_no=1077",
        "content": "2/4(화) 9시 ~ 3/18(화) 18시까지 국가장학금 2차 신청기간을 운영하오니,\n1차 신청 기간에 신청하지 못한 학생들은 필히 신청 바랍니다. [\"2025년 1학기[44\\n국가잠학금 신첨기간\\n'25.2.4.(화) 9시 a     |\\n\\n~3.18.(화) 18시   2 ;\\n\\n터,                     [\\n\\neer aaa |                                             :\\n\\nㅣ신청대상                             IMAM 및 가구원 동의기간\\n\\n신입고3, 재수생 통입화에절지) 편입생,  '25. 2. 4.(와) 9시 ~ '25. 5. 25.[화)78시\\nTHEI, Weta 및 1차 신첨블 봉친 재학생 ㅣ ㅣ, 포교을 대삼자는 온라인으로 서류제드 일시\\n\\n< 0646 7자전청이뢰이며, 자하 20어 새 ?시신지으 세즈 0 선철 2-3일 무 서랭페뜨 대실 며부를 반드시 확인이세요.\\n\\n \\n\\n \\n\\n바번                     누리집 NAL AAW REIS\\nㅣ신첨방법                     SSH Node tates\\n2 전지서명수탄한가지준비\\n.020인6서 6 2롤인6서 @간민요                       *＊ 하자금지원구간은 하생과가구원(부도또는배우자)이\\n소득평가액, 재산의소독환산액,험제자애수에 따른\\n< 안국잠아재탄 누리집 및 모바일앰매서 신정             공지멕을 반염하여 산정합니다\\nvwvrshoant goske\\nIalgzel\\n만피장외재탄상담벤터       a\\n1599-2000       BEE\\n\\n                                                                                                                                                                                                      \\n\\n \\n\\x0c\"]"
    },
    {
        "title": "2025학년도 1학기 국가근로장학금 (2차) 신청 안내(2. 4. 9시 ~ 3. 18. 18시)",
        "url": "https://www.jj.ac.kr/jj/community/notice/janghaknotice.jsp?mode=view&article_no=445954&amp;board_wrapper=%2Fjj%2Fcommunity%2Fnotice%2Fjanghaknotice.jsp&amp;pager.offset=0&amp;board_no=1077",
        "content": "<2025학년도 1학기 국가근로장학금 (2차) 신청 안내>\n2025학년도 1학기 국가근로장학금(2차) 학생 신청기간 및 신청 방법을 안내해드립니다.\nㅇ 국가근로장학금이란?: 지정된 근로지에서 근로하고 그에 따른 장학금을 월별 수혜\nㅇ 신청 대상:\n- 하계방학집중근로(2025년 7월~8월) 활동 희망자로,\n※ 금번 국가근로 2차 신청자는\n학기중 국가근로(2025년 3월~) 참여는 불가\n합니다.\n※\n국가근로 1차 신청자 중 하계방학집중근로에 참여를 희망하는 학생은 추후 희망근로지 신청만 진행하시면 됩니다(4~5월 중).\n금번에 국가근로 2차 신청을 다시 할 필요가 없습니다.\n- 우리 대학 정규학기 재학생 중 직전학기(2024-2) 백분위 성적이 70점 이상이며,\n- 당해학기(2025-1) 학자금지원구간(소득분위) 9분위 이하인 학생\n※ 근로장학사업 간의(국가근로 학기중, 보람근로, 대학생 청소년교육지원사업 등) 중복 참여 불가\nㅇ 신청 기간: 2025. 2. 4.(화) 09:00 ~ 3. 18.(화) 18:00\n(서류제출 및 가구원동의 기간: 2025. 2. 4.(화) 09:00 ~ 3. 25.(목) 18시\nㅇ 신청 방법:\n한국장학재단 홈페이지 또는 모바일 앱(상단 붙임문서 참고)\nㅇ근로 내용:\n- 하계방학집중근로 기간: 2025년 7월~8월 중\n- 근로지: 전국 교외 기관으로 주로 (준)공공기관(★ 교내 근로지는 미운영)\n- 시급: 12,430원(최대 근로시간은 300시간 내외로 변동 가능하며, 정확한 근로 기간 및 최대 근로 가능 시간은 추후 안내)\n- 하계방학집중근로 희망근로지 신청 필수(희망근로지 신청을 해야 신청이 최종적으로 완료됨): 2025년 4월~5월 중\n* 희망근로지 신청 기간은 한국장학재단에서 지정하며, 추후 학교 홈페이지 공지 예정\nㅇ문의\n- 한국장학재단 홈페이지, 모바일 어플 시스템 오류 등 문의 사항 1599-2290\n- 학생지원실 063-220-2162, 2172 ['이미지 없음']"
    },
    {
        "title": "중소기업 취업연계 장학사업(희망사다리1유형) 의무종사 기업기준 안내",
        "url": "https://www.jj.ac.kr/jj/community/notice/janghaknotice.jsp?mode=view&article_no=442807&amp;board_wrapper=%2Fjj%2Fcommunity%2Fnotice%2Fjanghaknotice.jsp&amp;pager.offset=0&amp;board_no=1077",
        "content": "중소기업 취업연계 장학사업 장학생은 아래 내용 필참하시기 바랍니다. ['Sidiwre                             한국장학재단                                oh\\n\\n \\n\\n \\n\\n;                   t         2\\n안내드리오니, 장학생 SA(Soil) 후 의무종사 미행 안내에 적극적인 활용을 요청 드\\n립니다\\nO ISSA SA SAIS WE\\n\\n \\n\\n구분                       인정불가 기준\\n\\n \\n\\n대기업, 중견기 멈(매출액 5.000먹원 초과), 비영리법인,\\nABER         국가-지방자치단체, 공기업-공공기관 및 자회사, 비사업자-종교단체\\n외국법인, 부모기업(부 또는 모가 대표자)\\n\\n \\n\\n \\n\\n계약방식       프리랜서, 특수형태 근로종사자(예 : 보험설계사, 택배원 등)\\n\\n \\n\\n취업지원형 | 청소년유해업소, 주점업, 사행시설 등\\n\\n \\n\\n창럽지원혈\\n\\n \\n\\n \\n\\n소속학과에 따른 진로 안내 필요\\n[유마교육] 어린미집-유치원 중 비멸리기관민\\nZI\\n\\nJ 82a 중 비명리기\\n\\n  \\n\\n기타\\n\\n \\n\\n \\n\\n \\n\\n \\n\\n \\n\\n니 의무종사 보고 방법\\n\\x0c', '빙자료를 재단 홈페이지로 보고\\n\\n \\n\\n춰 창업 기간 확인\\n\\n \\n\\n건강보험자격득실확인서\\n(또는 4대보험 가입기간 증빙서류)\\n\\n \\n\\n \\n\\n \\n\\n|업확인서)       부가가치세과세\\n\\n \\n\\n \\n\\n \\n\\n준증명원 등\\n\\n \\n\\nㅣ 기준의 주요내몽이며, 학기-사례에 따른 변동\\n\\n업무처리기준 확인이 필요함\\n\\x0c']"
    },
    {
        "title": "국가보훈장학금 국고보조금 신청 안내",
        "url": "https://www.jj.ac.kr/jj/community/notice/janghaknotice.jsp?mode=view&article_no=355705&amp;board_wrapper=%2Fjj%2Fcommunity%2Fnotice%2Fjanghaknotice.jsp&amp;pager.offset=0&amp;board_no=1077",
        "content": "국가보훈대상자 국고보조금 신청 안내\n국가유공자 등 예우 및 지원에 관한 법률에 따라, 국가유공자 본인 또는 가족에게 장학금을 지급하고 있습니다.\n대상자는 보훈처에서 해당 서류를 발급받아 학생지원실로 제출해주시기 바랍니다.\n◎ 대상자 여부 확인 및 서류 발급: 해당 지역 보훈처에 문의\n◎ 서류 안내\n구분\n제출 서류\n비고\n국가유공자 본인  또는 배우자\n교육지원대상자증명서\n3개월 이내 발급분\n국가유공자의 (손)자녀\n대학수업료등면제대상자증명서\n〃\n◎ 장학금액\n- 본인: 수업료 전액(초과학기 포함)\n- (손)자녀: 수업료 전액(정규학기 8회) - 단, 직전학기 성적 70점이상 유지하여야 계속 수혜 가능\n◎ 제출기간: 최소 당해학기 시작 1개월 전에 제출하여야 당해학기부터 적용 가능(1학기는 1월 말, 2학기는 7월 말)\n- 금번 2023-2학기는 2023. 8. 3.(목) 16시까지 제출하여야 적용가능\n- 이미 수혜받고 있는 학생은 제출하지 않아도 됨\n◎ 참고사항: 최초 1회 제출(면제여부 검토 후 계속 지급)\n◎ 제출처 및 문의: 전북 전주시 완산구 천잠로 303 학생회관 226호 학생지원실 (063-220-2982) ['이미지 없음']"
    },
    {
        "title": "★교내외 장학금 수령 계좌 inSTAR 등록 방법 안내★",
        "url": "https://www.jj.ac.kr/jj/community/notice/janghaknotice.jsp?mode=view&article_no=351217&amp;board_wrapper=%2Fjj%2Fcommunity%2Fnotice%2Fjanghaknotice.jsp&amp;pager.offset=0&amp;board_no=1077",
        "content": "교내외 장학금 수혜용 계좌 inSTAR 등록 방법 안내\n♣ 입력기간 : 상시\n♣ 입력방법\n- inSTAR → 장학/등록 → 장학관리 → 장학금 지급계좌관리\n- 지급계좌 변경 시, 재입력 후 저장시 등록완료\n♣유의사항\n- 본인 계좌 가능(부모, 형제, 친구, 지인 계좌  불가)\n- 입출금 통장 가능(청약, 적금통장, 휴면계좌 등 불가) ['Mle See\\n(1) 장학/등록 > 2) 장학 관리 (장학금 지급계좌관리) ~> 6 학생 본인 통장계좌 입격 0000엔\\n\\n간편등록!\\n\\n \\n\\notto\\n\\nCEs (eit)\\n\\n \\n\\n \\n\\n  \\n     \\n   \\n\\nith\\n\\nClee rr)        LS\\n\\nUsername\\n\\nD LyQ] Alea\\nPassword\\n\\n\" 대확에서는 국가장학금을                 장학금,             현금 지급하는 모든 형태의 장학금을 상기에 입력한 계좌를 동해 ?               ca\\n국가장학금을 포함하여 한국장학            도 가능한 이 계죄와 동일하게 관리하여 주시기 바랍니다:                                 ㅣ\\n\\nae. 기타 타인의 계좌가 0                 의 계좌이어야 하며,\\n유로 계좌를 변경해야 할 경                   } 계좌는 재학기간\\n\\n무지급계좌이력\\n\\x0c']"
    },
    {
        "title": "(한국장학재단) 2025년 특별상환유예대출  홍보",
        "url": "https://www.jj.ac.kr/jj/community/notice/janghaknotice.jsp?mode=view&article_no=446174&amp;board_wrapper=%2Fjj%2Fcommunity%2Fnotice%2Fjanghaknotice.jsp&amp;pager.offset=0&amp;board_no=1077",
        "content": "자세한 사항은 하단의 내용을 참고하시기 바랍니다. [' \\n\\n \\n\\n \\n\\n \\n\\n \\n\\n \\n                                                                                                                                                                                                                                                                   \\n\\n일반상환학자금대출 상환부담\\n\\n최대 3년 유예 가능!\\n\\n                                                                                                                                                                                                                                                                     \\n\\n \\n\\n \\n\\n \\n\\n \\n\\n첨대상           유예방식           유예대상           상환방식\\n만35세미하 최대3년간 일반상환학자금 4년분할남부또는\\n학부 졸업생            윈리급 대남             대출 전체            만기일시상환\\n\\n(기본 요건) 일반상환학자금대출 보유자 중 만 35세 이하, 학부 또는 대학원 졸업자\\n. (주가요건) 부모의 사망-까산:면책, 본인미 수급자-장애, 실직-페업 등 사유 발생\\n\\n한국장학재단 홈페이지 S! Sure! COA AI (www.kosaf.go.kr)\\n\\n한국장학재단 상담센터(1599-2000)\\n\\x0c', '유예대출이란?\\n\\n을 최대 3년 유예 - 유예금액은 별도 대출로 구성\\n| 분할상환(4년 간) 또는 @만기 일시상환(4년 후)\\n\\nu\\n\\n|나에 해당되면 신청 가능\\nAt\\n\\n복무(예정)자 + 연체 3개월 이상(졸\\n인 실직-폐업\\n\\n[> 부모 파산ㆍ면책-개인회생\\n\\n가계곤란 ㅣ(> 본인 기초ㆍ차상위\\n\\n[> 본인 기한이익상실예정\\n\\n[> 본인 보이스피싱ㆍ불법사금융피해\\n\\n[> 부모 사망\\n\\n는\\n가\\n=\\nNo\\n\\no | md4}\\n\\n[으1\\n\\n0&\\n= Oot | Mt\\nwI0\\n\\nOM | FHE | OS rz\\n\\n \\n\\nHS SHA (SHS eH) - SASS) -(SSS2 SOSA VSS 2 MBM Sel tS            |\\n\\n문의: 한국장학재단 상담센터(1599-2000)\\n\\x0c']"
    },
    {
        "title": "해양수산부 극지연구 전문인력 양성 장학금 신규 장학생 선발 공고(~2. 3.)",
        "url": "https://www.jj.ac.kr/jj/community/notice/janghaknotice.jsp?mode=view&article_no=446078&amp;board_wrapper=%2Fjj%2Fcommunity%2Fnotice%2Fjanghaknotice.jsp&amp;pager.offset=0&amp;board_no=1077",
        "content": "자세한 사항 붙임 파일 참고 ['여 바랍니다.\\n\\n1\\nol\\n\\n~ 진\\n2025년 01월 15일\\n\\n성 장하급\\n그\\n\\n제3차 신규 장학생 선발 공\\n장학사업」 의 제3차 장학생을 모집,\\n\\n양성\\n\\n제2025-69호\\n¥\\n력\\n\\n선발하고자 하오니 극지분야에 관\\n\\n \\n\\n \\n\\n패\\n\\n아\\nJ\\nss\\n\\nOn\\n\\n:사회)에 지속적으로 기여할 수\\n\\n학기술-인문\\n\\n구(과\\n\\n마련을 목적으로, 국내 석:박사 과정\\n\\n책\\n\\n시\\n\\n원\\n\\nial\\n\\n양성하기 위하여\\n\\n으\\n글\\n\\n}련 전문인력\\n\\n국가는 극지 관\\n\\n \\n\\n를 제9조(전문인력의 양성)\\n\\nHY\\na\\n\\n*\\n\\n|\\n\\n우\\n\\n개받\\n\\n|] 신청대상\\n\\n \\n\\nKo\\n\\n시점으로부터 2년이 경과하지\\n\\n생 및\\n\\n재학\\n\\n가능\\n\\n해\\n2\\n+\\na\\nio\\n\\n야\\n\\n에\\nTH\\n긴\\n\\n=0\\nBl\\n해\\nor\\n\\x0c', '발계획\\n\\nor\\n0\\n\\n시\\n\\n도\\n\\n9\\n\\n2025\\n\\n \\n\\n \\n\\n \\n\\nOu &\\n\\n \\n\\nO 제3차 장학생 지원 기간\\n\\n- 2025년 3월/25.1학기) ~ 2026년 12월(26.2학기)\\n\\n제출에 따,\\n\\n1 7\\n\\n원\\n\\nro\\n\\n|며, 최대 4학기까지 지\\n\\n원히\\n\\n기까지 장학금 지\\n\\n전 최종학\\n\\n직\\n처전\\n\\n료\\n\\nfob\\n\\n}생 대상 4\\n\\n히\\n\\n최대 10백만원 내외 지원, 2인 장\\n\\n80백만원 내 지원\\n\\n1인당\\n\\n준 종\\n\\n기 기\\n\\nＬ\\n\\n왁\\n\\n \\n\\n드\\n\\n*\\n\\n[동비(연구장비비, 연구재료비, 연구자료\\n\\n활\\n활\\n\\nㅋ 전액과 연구\\n\\n극 및 입\\noO 츠 트\\n\\noo\\n\\nAME 및 기타 연구에\\n\\n논문\\n\\n록비,\\n\\njou\\n\\negw\\n용등포\\n\\n필수 활동에 따른 소요 4\\n\\n[| 신청자격\\n\\nKo\\nee\\n°\\n\\na\\n때\\n때\\nqr\\n\\naK\\n°\\n\\nah\\nqr\\n\\nOF\\n‘Bp\\nKo\\nel\\n\\n001) 등\\n\\n연구 분야\\n나. 극지 조선, 에너지, 광물\\n\\n및 수산\\n\\x0c']"
    },
    {
        "title": "2025-1학기 목회자 및 목회자 자녀 장학금 신청 안내",
        "url": "https://www.jj.ac.kr/jj/community/notice/janghaknotice.jsp?mode=view&article_no=445984&amp;board_wrapper=%2Fjj%2Fcommunity%2Fnotice%2Fjanghaknotice.jsp&amp;pager.offset=0&amp;board_no=1077",
        "content": "2025-1학기 목회자 및 목회자자녀 장학생을 다음과 같이 선발하고자 하오니 해당 학생들은 신청기한 내에 선교지원실로 신청서와 제출서류를\nFAX(063-220-2066)로 제출해주시기 바랍니다.\n1.선정인원\n가.목회자 장학금: 00명\n나.기독교목회자자녀장학금: 00명\n2.장학금액\n가.목회자 장학금: 1인당 1,000,000원(수업료 범위 내)\n나.기독교목회자자녀장학금: 1인당 500,000원(수업료 범위 내)\n3.선정기준\n가.목회자 장학금\n1)본교 재학생으로 본인이‘목사’, ‘전도사’로 사역 중인 자\n2)국가장학금 신청자로서 소득분위 8분위 이내인 자\n3)직전 학기(2024-2)취득학점 12학점 이상 및 평점평균 2.5이상인 자\n나.기독교목회자자녀장학금\n1)본교 재학생으로서 부모님이‘목사’로 사역 중인 자\n2)국가장학금 신청자로서 소득분위 8분위 이내인 자\n3)직전 학기(2024-2)취득학점12학점 이상 및 평점평균2.5이상인 자\n4.제출서류\n가.노회(지방,시찰,시타)발행 재직증명서1부(전도사의 경우 교회 발행 재직증명서)\n나.가족관계증명서 또는 주민등록등본1부\n다.교회 주보1부(최근3주 이내)\n라.장학금 신청서1부*[붙임]\n5.제출 방법 및 문의처\n가.제출 방법: 2월 6일17:00까지 선교지원실FAX(063-220-2066)제출\n나. 문의처: 063-220-2103 (담당: 오예찬) ['이미지 없음']"
    },
    {
        "title": "한국장학재단 글로벌 현장학습 사업 소개(파란사다리, 한일 대학생 연수)",
        "url": "https://www.jj.ac.kr/jj/community/notice/janghaknotice.jsp?mode=view&article_no=445715&amp;board_wrapper=%2Fjj%2Fcommunity%2Fnotice%2Fjanghaknotice.jsp&amp;pager.offset=0&amp;board_no=1077",
        "content": "자세한 사항 붙임 파일 참고 ['현장학습\\n글로벌      장학\\n\\n소개 및 안내\\n사업\\n\\n학샘 연수)\\ncaret, 2-2 4\\n\\n \\n\\x0c', ' \\n \\n \\n\\n아게 새알 가\\n\\n \\n\\n파란사다리\\n자기개발과 진로개척에 꼼과 열정을 지닌 대학생몰 위한 해외연수 프로그램\\n+ 신첨대상: 국너 너학에 새학줌인 점세적 사회적 취약계층 다흐셈\\n\\n+ 지원내음: 항곰비. 기숙사비. 련시 교육비 등\\n\\nHE AGH] AIS\\n\\n라라\\n\\n.2우총: 15당 900만 원지원(5뉴기증 6주|\\n\\n한일 대학생 면수\\n때학생에게 일본 현지 머학연수 현장학습 및 문화생활 기회를 체공하여 글로벌 역량 강화 지원\\n+ 신청대상: 국내 내학에 재학중인 내학셈(내학 4학기 이삼, 즈문다학 ?화기 이삼 이수사\\n\\n1원내용: 상 호습비 1인당 860한 원 시:\\n\\n \\n\\nMLB 16% oles)\\n\\n한-미 THE} O1-(WEST: Work English Study Travel)\\n\\n때확생에게 미국 인턴십 기회를 제공하며 글로벌 감각을 갖춘 핵삼인채 망성\\n신청대상: 4년제 내학 화기 이상, 즈문다학 화기 이상돌 이수한 서휴허\\naga\\n\\nay ci\\n\\n \\n\\n+ 지원내용: 학자금 시유구가별 치듬 시웨신가비 생림비> 및 등 시웨황공비!\\n\\n우수고등학생 해외유학 장학금(드림장화2)\\n저소득층 무수고등학생에게 해외유학 기회를 체공해 글로벌 인짜로의 성징들 지원하는 장학금\\n+ ASG BU ABER Oe Bee tat\\n\\n유확주티능[고등확생/ㆍ딱커잠켜티(배정 그 60만 원 고 70만 원)\\nPRM DA Cle Ee Aa Iu 6B! USD 6 ts\\n\\n \\n\\n자 자조 은 비래\\n\\n \\n\\x0c']"
    },
    {
        "title": "2025년 1학기 한국장학재단 푸른등대 기부장학금 신청 안내(12.27.~25.1.20 18시)",
        "url": "https://www.jj.ac.kr/jj/community/notice/janghaknotice.jsp?mode=view&article_no=445509&amp;board_wrapper=%2Fjj%2Fcommunity%2Fnotice%2Fjanghaknotice.jsp&amp;pager.offset=0&amp;board_no=1077",
        "content": "자세한 사항 붙임 파일 참고 ['이미지 없음']"
    },
    {
        "title": "(신청기간 연장)2025년 1학기 한국농어촌희망재단 청년창업농장학금 신청 안내(~25. 1. 13. 17시까지)",
        "url": "https://www.jj.ac.kr/jj/community/notice/janghaknotice.jsp?mode=view&article_no=445503&amp;board_wrapper=%2Fjj%2Fcommunity%2Fnotice%2Fjanghaknotice.jsp&amp;pager.offset=0&amp;board_no=1077",
        "content": "신청 기간 연장: ~25. 1. 13. 17시까지\n자세한 사항 붙임 파일 참고 [' \\n\\n신청기간\\n\\n900명 내외\\n\\n선발인원\\n\\n선\\n\\n학생\\n\\n|기 이상)의 만 40세 미만\\n\\na\\not\\n\\n2\\n\\n스마트폰으로\\n\\n \\n\\n \\n\\nRO\\nx1\\n\\nx\\n2\\n=\\n8\\nnd\\n으\\nxo\\n5\\n=\\n=\\n2\\nq\\n으\\n벼\\n00\\n0\\ngE\\na\\n\\n \\n\\n02-6958-9464)\\n\\n전화(\\n\\n재단 대표\\n\\x0c']"
    },
    {
        "title": "제29회 (재)부산진구장학회 장학생 선발 계획 공고(1. 6.~1. 17.)",
        "url": "https://www.jj.ac.kr/jj/community/notice/janghaknotice.jsp?mode=view&article_no=445488&amp;board_wrapper=%2Fjj%2Fcommunity%2Fnotice%2Fjanghaknotice.jsp&amp;pager.offset=0&amp;board_no=1077",
        "content": "자세한 사항 붙임 파일 참고 ['AGNES\\n\\n«ere\\n\\n}여 주시기 바랍니다,\\n2024년 12월 20일\\n글\\n\\n정히\\n\\n|재)부산\\n자는 신청\\n\\n2.\\noO\\n\\n—_|\\nAH\\n\\n29:\\n\\n \\n\\n \\n\\n \\n\\n \\n\\n \\n\\n \\n\\n \\n\\n \\n\\n \\n\\n \\n\\n \\n\\n \\n\\nZi     !\\n후 | 한 B/e |e) ze #\\n(8/2 )2| 2 |\\nalia} Sis 2/3 /¢\\nnlel|s Ble] S ft            dl\\nBlefEloejs =             ‘\\nS|) 7 |m\\n:                Ha\\n-                uo                       에 회\\n        _        대\\nr           =z        iK|O         ig\\ntp    # |e] els        =       ua\\n<     2 한\\nio   S  B/E le              ch\\n는       웅 | 운 | 응 중              iy                \"|\\n0    7    in a                 :\\nB/S\\n회           호        조개\\n         1        dit\\n= 5          <    nq  까 =     “| #\\nB     5   3\\n리리 |       z     Blair 을 4      어데 본\\n다 흐흐  at y  ai =\\na    8/2) 20      | @ 그       주신   0\\n!  ie           일        들 없죠       a  ir\\n3  6  ,      5       ilo! De\\n| 웨드 |  0 | 이 |페     기 두 자       zl x  :\\n|Z           z          ®      x    E\\n대 | 자               *      기 퍼 tr          a8   .\\nz     ‘| AS) ito        2] x\\n590              | ot     iS] ak Sf a       as   -\\nod       % | RO   S| = 0r 푸    회피 -\\n                     그\\na | 패    wo | =  for | ae     NESE      wz 8\\nin       ze    F       ae           :\\nmW] | < |또 or | =   Gua #    i: :\\nB\\n다        | | 호      eu ad #      z\\nio            Br    고조 8 FO    a     a\\n—_     x       4    7 a    i\\n1              K      ~e £ ce       주    if\\n:                  때 RP ke   a    ® i    밤\\na                    x 고 고    :       내    !\\nCero    mi Re\\n고\\nos 풋   *\\n\\n \\n\\n년 3과목(국어:\\n년 3과목(국어:\\n\\n+\\n\\n더\\n\\n+\\n\\n호\\n더\\n\\na]\\n\\n: 해당:\\n: 해당\\n\\n인문계\\n\\noO\\n\\x0c', \"학년 기\\n\\n※ 2024년도\\n\\n학, 4년제 대학\\n\\n3\\n\\n년) 『 전문대\\n\\nTL\\n\\n호\\n더\\n\\n나. 대학생(123\\n\\n인 자(만점 4.5기준)\\n\\n4. 지원기준\\n\\n* 대학생 국가장학금(등록금 명목)의 경우 중복수혜 가능\\n\\n5. 장학생 선발(신청) 제외대상\\n\\n9\\n받는 육\\n\\n을 지원\\n\\n저이\\n4\\n\\n선\\n\\n록금과 수업료가 면제되거나\\n\\nule\\n\\n‘or\\n\\n른 지방자치단체나 무\\n\\n다. 다\\n\\n신청 시는 예외)\\n\\n학금을\\nToS\\n\\n회 장\\n\\n하고 본 장학:\\n\\n학금을 포기\\n\\n(*단, 타 단체 장'\\n\\n}인 자(2024년도 기준)\\n\\n업예정자 (2025년 졸업자)\\n\\nBe\\n=\\n\\n로서\\n\\n+\\n\\n냉에 한함\\n\\nSHI\\n더\\n\\n선문대 대\\n\\n및 ※\\nwz\\n\\nYe 4A\\n\\n바. 대학생\\n\\n사. 부모가\\n\\nAQ\\n\\n토지 : 공시지가 적용\\n\\nOo\\n\\n시지가) + 건물 과세시가표준액 적용\\n\\nㅇ\\n\\n \\n\\n가 건물 - 토지(\\n\\n상:\\no\\n\\x0c\"]"
    },
    {
        "title": "2024-2학기 국가근로장학금 신규장학생 운영 안내(대체선발, 동계방학집중근로)",
        "url": "https://www.jj.ac.kr/jj/community/notice/janghaknotice.jsp?mode=view&article_no=445332&amp;board_wrapper=%2Fjj%2Fcommunity%2Fnotice%2Fjanghaknotice.jsp&amp;pager.offset=0&amp;board_no=1077",
        "content": "2024-2학기 국가근로장학금 신규장학생 운영 안내(대체선발, 동계방학집중근로)\n국가근로장학사업 주요 운영 사항 및 근로 시작 전 필수 실시 사항을 안내하오니 반드시 숙지하시고 진행해주시기 바랍니다.\n1.\n근로 시작 전\n필수 실시 사항\n(아래 그림과 첨부파일 참고)\n가. 서약서 작성 및 사이버 O.T. 수강\n(장학재단 홈페이지) -첨부파일 13~15P참고\n나. 학업시간표 등록★\n-첨부파일16~18P참고\n-계절학기 수강자만 해당\n-장학재단 지침상, 수업시간에는 근무할 수 없음. 학업시간표를 등록해두고 그 시간 외에 근무하고 출근부를 입력하는 것이 학업시간표 등록의 목적임\n-진로설계세미나(진로탐색)과목 등도 시간표에 반드시 등록\n-★학사시스템에 등록된 그대로 정확한 수업시간표 입력\n(입력된 수업시간표가 실제와 달라 부정근로 등의 문제 발생 시, 장학생 본인에게 책임이 있고 장학금 환수, 근로 참여 제재를 받게 됨)\n-일시적인 휴강이 발생하여도 그 시간에는 근로 불가하고 인정되지 않음\n-온라인 수업이어도 학사 시스템상 수업 시간이 정해져 있는 경우, 반드시 입력해야 함\n다. 업무스케쥴 입력\n-첨부파일 19~21P참고\n-어떤 요일에 몇 시부터 몇 시까지 몇 시간 동안 근무할지 근로 시간표를 정하는 것\n-학생이 근로지에 전화하고 담당자와 상의하여 업무스케쥴 작성\n(별도로 보낸 문자 링크 클릭하여 연락처 정보 확인 요망)\n-아래 ‘최대 근로 가능 시간’을 참고하여 범위 내에서 업무스케쥴을 작성\n-작성한 업무스케쥴을 출근부 어플에 입력해야 하며, 업무스케쥴을 입력하여야 출근부가 활성화 됨\n<일/주/월별 최대 근로 가능 시간>\n-대체선발-\n1일 최대 8시간, 1주 최대 25시간, 1개월 최대 90시간(1월, 2월 각각)\n-방학집중근로-\n1일 최대 8시간, 1주 최대 40시간, 1월~2월 전체 최대 220시간(변동 가능)\n2. 근로 시작 후 필수 실시 사항(아래 그림과 첨부 파일 참고)\n가. 사전교육 이수보고서 작성 및 제출\n(근로지 담당자에게 교육을 받은 후 보고서를 작성하고 담당자 서명을 반드시 기입하여 장학재단 홈페이지에 탑재, 방법 첨부파일 22~24P 참고)\n-양식: 첨부파일 참고\n나. 근로지 상호평가(근로지 담당자와 학생이 상호 평가, 첨부파일 32P 참고)\n- 근로 시간\n40시간 초과 시 1차 평가 필수, 160시간 초과 시 2차 평가 필수\n※가, 나. 미이행 시 출근부 제출이 안됨\n3. 출근부 입력 및 제출 관련 사항\n가. 출근부 입력 방법(붙임 첨부파일 25~28P 참고)\n나. 출근부는 출퇴근 즉시 입력이 원칙\n다. 불가피하게(출근부 앱 오류) 출근부 입력이 안된 경우, ★근로지 담당자에게 수정 요청\n(단, 수정 횟수의 제한이 있으며, 수정이 계속될 경우 향후 한국장학재단의 부정근로 모니터링 대상이 될 수 있음)\n라. 점심시간은 근로 시간에서 제외\n마. 근로지에서 출근부 대학제출이 익월 초일까지 이뤄질 수 있도록 협조\n(1개 근로지라도 제출이 늦어질 경우 장학금 지급 지연될 수 있음)\n4. 주요 운영 사항\n가. 근로 기간\n- 대체근로: 2024. 12. 23.(월)~2025. 2. 28.(금)\n- 동계방학집중근로: 2025. 1. 2.(목)~2025. 2. 28.(금)\n나. 시급: 교내 10,030원 / 교외 12,220원\n다. 장학금 지급일: 익월 15일 경\n(1월 근무분은 2월 15일 경에 국가근로 신청 시 장학재단에 입력한 계좌로 입금, 출근부 제출 지연 시 지급이 지연될 수 있음)\n라. 일/주/월별 최대 근로 가능 시간\n-대체선발-\n1일 최대 8시간, 1주 최대 25시간, 1개월 최대 90시간(1월, 2월 각각)\n-방학집중근로-\n1일 최대 8시간, 1주 최대 40시간, 1월~2월 전체 최대 220시간(변동 가능)\n마. ★국가근로 장학생 준수 사항 및 근로자격 해제 사유\n국가근로 장학생의 경우 ‘다음’ 내용을 준수하여 근무하여야 한다.\n다음 내용 중 ‘\n1-4번’을 준수하지 않아 근로지 담당자로부터 2회 이상 경고를 받고 개선하지 않을 경우, 또는 ‘5-6번’에 해당할 경우,\n근로지 담당자는 학생지원실로 해당 학생의 “근로 중지”를 요청 할 수 있다.\n학생지원실은 “근로 중지”를 요청 받은 다음날부터 해당 학생의\n“근로 자격을 해제”\n한다.\n근로 자격을 해제 받은 시점부터 해당학기 근로(국가근로, 대학생 청소년교육지원사업, 보람근로)장학에 참여할 수 없다.\n-다음 -\n1. 출.퇴근 시간을 준수하며, 무단결근과 근로지 무단이탈을 하지 않는다.\n2. 근무지의 합리적인 업무 요청에 특별한 사유없이 불응하거나 직무태만하지 않는다.\n3. 부정근로를 하지 않는다.(근로시간 허위 입력 등)\n4. 기타 근로장학생으로서 근로 태도가 불량하거나 의무를 다하지 않는 일이 없도록 한다.\n5. 배정된 근무지에서 근로학생이 업무수행이 불가능하다고 할 경우 ‘근로 중지’ 된다.\n6. 학사징계 혹은 법적 처벌을 받은 경우 ‘근로 중지’ 된다.\n5. 기타 중요 사항\n가. 근로장학은\n학적이 ‘재학’인 경우만 실시 가능함. 학적변동 시 근무 불가(휴학/자퇴 ‘신청일’ 전날까지만 근무 가능하며, 제적/졸업 ‘발생일’ 전날까지만 근무 가능함), 졸업유예학생은 2월 28일까지 근무 가능.\n나. 타 장학사업과 중복 근로할 수 없음\n(보람근로, 대학생 청소년교육지원사업, 학기중에 국가근로에 참여한 경우 방학집중근로에 지원 불가)\n다.\n부정근로(허위근로, 근무시간 오입력, 대체근로-실제 근무 시간과 출근부에 입력한 시간이 다른 경우, 대리근로 등) 적발 시 졸업 시까지 사업 참여 불가 및 장학금 반환\n라. 출근부 제출은 익월 첫째날까지 완료되어야 함\n마.\n근로지 담당자 또는 직원과 가족관계, 친인척 관계, 기타 이해관계가 있는 경우 근로 불가\n하며, 해당 시 학생지원실 담당자에게 통보해야 함\n바. 문의 전화: 출근부 어플 및 홈페이지 오류 등: 한국장학재단 콜센터 1599-2290 [\"전교육\\n이수보고서\\n\\n \\n\\n \\n\\nt\\n\\n'\\n\\n'\\n\\nㅣ\\nej!\\neo\\nao\\nK 해도 1\\nm “ZS\\n\\nxe\\n본 | 때 |\\n\\niH ee1\\n\\nvo\\n\\n‘ “\\n미움\\n—_—                zu\\n\\n비                 101                         내몬\\nKd            -\\n\\x0c\"]"
    },
    {
        "title": "2025년 (재)협성문화재단 협성장학생 선발 안내(12. 16.~2025. 1.6.)",
        "url": "https://www.jj.ac.kr/jj/community/notice/janghaknotice.jsp?mode=view&article_no=444552&amp;board_wrapper=%2Fjj%2Fcommunity%2Fnotice%2Fjanghaknotice.jsp&amp;pager.offset=0&amp;board_no=1077",
        "content": "자세한 사항 붙임 파일 참고 ['$4 때)협성문화재단\\n\\n수신지\\n\\n+\\n=\\nPad\\nwt\\nbi\\n\\n(참조) 교외장학담당자\\n제 목 『2025년 신규 협\\n을\\nz\\n\\n1. 귀 교의 무궁한 발전\\n\\n가. 지원 대상 : [부산.울산.경남지역 고교출신]전형\\n국내 4년제 이상 대학교의 신입생 ce      년\\n[견설근로자 자녀]전형 - 건설근로자공제회 기준 총 적립일수 756일\\n\\n미상미면서 2024년도 근로내역이 100일 이상 적립된 피공제자의 자녀로,\\n국내 4년제 이상 대학교의 신입생 또는 2024년 기준 2~3학년 재학생\\n전형 20~30명 / [건설근로자 자녀]전형 20명\\n\\n나. 선발 인원 : (부산,울산.경남지역 고교출신]전\\n다. 지원 내용 : 등록금 및 매 학기 학습보조금(생활비) 50만원\\n라. 지원 방법\\n1) 접수기간 : 2024년 12월 16일(월) ~ 2025년 1월 6일(월)\\n2) 접 수 처 : 협성문화재단으로 우편접수등기우편/접수마감일 도착 분까지 인정)\\n마. 심사말정\\n1) 서류합격자 발표 - 2025년 1월 27일(월) *재단 홈페이지 게시\\n2) 면 접 심 사- 2025년 2월 3일(월) ~ 7일(금) 5밀간\\n3) 최종합격자 발표 - 2025년 2뭘 10일(월) *재단 흠페이지 게시\\n4) 장학중서 수여식 - 2025년 2월 14일(금) 불참 시 장학생 선발 제외\\n※줌요 : 2025년 신규 협성장학생 선발에 관한 자세한 내용은 첨부된 선발계획안을 참고 해주시기 바랍니다.\\n\\n붙엄 : 1) 『2025년 부산.울산.경남지역 고교줄션 대학생 신규 협성장학샘』선발계획만\\n1-1) 『2025년 건설근로자 자녀 대학생 신규 협성장학샘」선발계획만\\n\\n수신처 : 가야대학교 외 199개 대학교.\\n\\n재단법인 협성문화재단 이사\\n\\n \\n\\x0c']"
    },
    {
        "title": "2025년도 제1기 전주시 글로벌 인재양성  영어능력강화사업 장학생 선발 재공고(~11.29. 18시)",
        "url": "https://www.jj.ac.kr/jj/community/notice/janghaknotice.jsp?mode=view&article_no=444301&amp;board_wrapper=%2Fjj%2Fcommunity%2Fnotice%2Fjanghaknotice.jsp&amp;pager.offset=0&amp;board_no=1077",
        "content": "자세한 사항 붙임 참고 ['8\\n5\\n[모\\nHo\\n=\\nyg\\n[것\\n2\\nuu\\nHU\\nfle\\nre\\nas\\n3\\n\\n \\n\\n창조적 역량과 열린 마인드를 지닌 인재로서 우리 지역 발전에 기여\\n하고 세계를 향해 꿈을 펼쳐나갈 글로벌 우수인재를 발굴 육성하기 위히\\n영어능력강화사업 장학생을 아래와 같이 선발하고자 재공고합니다.\\n2024년 11월 25일\\n(재)전주인재육성재단 이사장\\n1 | 사업개요\\n1. 선발인원 : 10명[국민기초생활보장수급자(차상위계층 미포함) 1명 포함]\\n※ 제27| : 10명, 2025. 5-6월 모집예정\\n2. 선발대상 : 대학생(재학생 및 휴학생)  ※ 도내대학생 7명, 도외대학생 3명\\n※ 장학생으로 선발될 경우 2025년도 1학기를 휴학할 수 있는 학생\\n3. 연수기간 : 2025. 1월 ~ 6원 예정  ※ 제2기 : 2025. 7월 ~ 12월 예정\\n4 연수과정\\nㅇ 영어몰입 집중과정(국내)        : 2025. 1월 ~ 5원(약 5개원)\\nㅇ 해외단기체험연수(국외)         : 2025. 6원(약 0.5개원)\\n6 활동보고서 작성 및 보고회(국내) ： 2025. 6월(약 0.5개원)\\n\\n5. 지원내용 : 1인당 1350만원 이내 지원\\nㅇ 연수생 자부담 : 1인당 150만원(해외연수비용 중 일부\\nO 국민기초생활보장수급자는 1.500만원 한도내 100% 지원\\n\\n6. 선발방법 : 1차심사(서류), 2차심사(면접)\\n\\x0c', ' \\n\\noy\\n때 쪼\\nCaF\\n띠 개 와\\nhol od\\n    세 00 Rr\\n바 0     eA\\nee     to = ot\\nxo FF oll\\nB=     eee\\n5 버     Bus\\n× 호     7 에\\nKe     Hoe\\n+ Soe    바 해 <\\n고바 더    메바 별\\nBw F    “eR\\nKk F TK    ro\\nRK    훈족 분\\n시 그 더    오번 해\\n떠 은 허    ey\\nlo YYo <r  XOX\\nRm pil i  oo te\\nth    =\\nwo KE\\nOh <b <b 더 nN  ee\\n=, O BW  my aS 고\\nwo o 00 el 2 고깨펀\\nyf eR a 운 린호0\\nHl Oo oO oO   doo\\n\\n \\n\\n \\n\\n \\n\\n간 제왜\\n\\n|금 신청“에서 접쉬\\n부(사본불가)\\n\\n호\\n\\n|\\n\\na\\n점\\n\\nbod\\n\\n히\\n\\n자\\n승\\n\\nHh 2\\n\\n|여 타인에게 피\\n\\nBE\\n\\nㅎㅇ\\n주인재육성재단 누리집(장\\n\\n3\\n본 스캔 후 『마로 저\\n\\n부\\n\\n=\\nwa\\n\\n2\\n\\n: (재)전주인재육성재단 사무국(1.063-283-5501, 282-1813)\\n전주시 완산구 현\\n\\n: 2024. 11 25.(월 ~ 1. 29.(금. 1800까제트\\n\\n교생활 태도가\\n\\n1\\n\\n학\\n\\nroy\\nㅇ 방문접수:\\n\\n0 직전학기(학기) BAe! Bee}\\nOo\\n\\n11. 접수기간\\n13. 접 수 처\\n\\x0c']"
    },
    {
        "title": "(대학생 재직자)2024-2학기 고졸 후학습자 장학금 2차 신청 안내(11. 21.~11. 28. 18시)",
        "url": "https://www.jj.ac.kr/jj/community/notice/janghaknotice.jsp?mode=view&article_no=443940&amp;board_wrapper=%2Fjj%2Fcommunity%2Fnotice%2Fjanghaknotice.jsp&amp;pager.offset=0&amp;board_no=1077",
        "content": "자세한 사항 붙임 파일 참고 ['@ 222\\n\\n자 장학금이란?\\nPAPA RD ast\\n|자를 지원하는 장학금\\n\\n2024년 2학기 고줄 후학습자 장학금 (희망사다리 2유형)\\n\\n06529\\n\\n2024.11. 21.(목) 09시       + 중소종견기업:수혜 학기\\n\\n~2024.11.28.(목)18시        + 대기멈-비영리기관: 수혜혁\\nfo) aa\\n\\n대     국 국적자   최종학력이 고졸인 자\\n\\n직전학기 성적이 백분위 70점(09 이상인 자\\n재직기간이 2년 이상인 자\\n\\n조언 송수승견기업자직자는 1넌 미상\\n\\n현재 지원 대상기업에 재직 중인 자\\n\\n재 지원 대상기업에 재직     한국장학재단 누리집(640지) | 희망사다리 상담센터\\neg obbatelu 건    ：    www.kosaf.go.kr 1800-0499\\n\\n \\n\\x0c']"
    },
    {
        "title": "2025학년도 1학기 국가근로장학금 1차 신청 안내(11. 21. 9시~12. 26. 18시)",
        "url": "https://www.jj.ac.kr/jj/community/notice/janghaknotice.jsp?mode=view&article_no=443907&amp;board_wrapper=%2Fjj%2Fcommunity%2Fnotice%2Fjanghaknotice.jsp&amp;pager.offset=0&amp;board_no=1077",
        "content": "<2025\n학년도\n1\n학기 국가근로장학금\n1\n차 신청 안내\n>\n2025\n학년도\n1\n학기 국가근로장학금\n(1\n차\n)\n학생신청기간 및 신청 방법을 안내해드립니다\n.\nㅇ 국가근로장학금이란\n?:\n지정된 근로지\n(\n교내 부서 또는 교외 근로지\n)\n에서 근로하고 그에 따른 장학금을 월별 수혜\nㅇ 근로 기간\n: 2025\n년\n3\n월 개강\n~2025\n년\n8\n월 방학 종료 시까지\n(\n변동 가능\n)\nㅇ 신청 가능 대상\n(1~4\n를 모두 충족\n)\n1. 2025-1\n학기가 정규학기\n8\n학기 이하\n(\n단\n,\n건축학과는\n10\n학기 이하\n)\n* 2025. 8.\n졸업자는 졸업식 전날까지 근무\n2.\n재학생\n(\n휴학\n,\n자퇴\n,\n제적\n,\n졸업자 제외\n)\n3.\n직전학기\n(2024-2\n학기\n)\n백분위 성적이\n70\n점 이상\n4. 2025-1\n학기 학자금지원구간이\n9\n분위 이하\n※\n2025-1\n학기 신\n/\n편입생은\n1\n차 신청을 받지 않습니다\n(\n학기중 근로 불가\n).\n2\n차 신청 기간\n(2025\n년\n2\n월\n~3\n월 초 예정\n)\n에 신청하시면 하계방학집중근로\n(7~8\n월 방학중 근로\n)\n에 지원할 수 있습니다\n.\n※ 근로장학사업 간의\n(\n보람근로\n,\n대학생 청소년교육지원사업 등\n)\n중복 참여는 불가합니다\n.\n※\n*\n조기취업자\n,\n산업체 위탁생은 국가근로 참여 불가합니다\n.\n*\n조기취업자\n:\n재직증명서 및\n4\n대보험 가입내역이 확인되는 경우\n(\n단\n,\n일용직\n/\n아르바이트\n/\n체험형인턴은 조기취업자에 해당되지 않음\n)\nㅇ\n1\n차 신청 기간\n: 2024. 11. 21. 9\n시\n~ 2024. 12. 26. 18\n시\n※ 주말 및 공휴일 포함 신청기간 내\n24\n시간 신청 가능\n(\n단\n,\n신청 마감일 제외\n)\n★ 이번\n1\n차 신청 후\n,\n추후 희망근로지를 신청해야 신청이 최종적으로 완료됨\n-\n희망근로지 신청기간\n(\n예정\n): 2025. 2. 14.~2. 17.\n자정까지\n-\n별도로 희망근로지 신청 알림을 하지 않을 예정이므로\n,\n희망근로지 신청기간을 반드시 숙지하기 바람\nㅇ 신청 방법\n:\n한국장학재단 홈페이지 또는 모바일 어플 이용\n(\n첨부파일 참고\n)\n※ 선발 요건인 소득분위 산정에 시간이 오래걸리기 때문에\n,\n가급적 신청을 빨리 해주시기 바랍니다\n.\nㅇ선발 방법\n(\n변동 가능\n):\n희망근로지까지 신청한 학생 대상으로 심사하며\n,\n환산점수\n(\n학자금지원구간 환산 점수\n50% +\n직전학기 성적 환산 점수\n50%)\n고득점 자 순으로 선발\nㅇ\n2025\n학년도 하계방학 집중근로 프로그램\n(2025. 7.~2025. 8.\n중 교외 공공기관에서 집중근로\n)\n에 참여하고자 하는 경우에도\n,\n이번\n1\n차 또는\n2\n차 신청 기간\n(2025. 2\n월 중순\n~2025. 3\n월 초\n)\n에 국가근로장학금을 신청해야 함\n-\n하계방학 집중근로도 추후 희망근로지를 신청해야 신청이 최종 완료됨\n-\n희망근로지 신청기간\n: 2025\n년\n4\n월\n~5\n월 중 예정\n※ 상기 운영일정 등은 재단\n,\n대학 학사일정 등에 따라 변경될 수 있음\n[\n문의\n]\n어플 및 홈페이지 시스템 관련 문의\n:\n한국장학재단 콜센터\n1599-2290 /\n학생지원실\n063-220-2162, 2172 ['이미지 없음']"
    },
    {
        "title": "2025-1학기 국가장학금 신청기간(1차, 11/21~12/26) 안내",
        "url": "https://www.jj.ac.kr/jj/community/notice/janghaknotice.jsp?mode=view&article_no=443614&amp;board_wrapper=%2Fjj%2Fcommunity%2Fnotice%2Fjanghaknotice.jsp&amp;pager.offset=0&amp;board_no=1077",
        "content": "2025학년도 1학기 국가장학금 신청기간을 다음과 같이 안내하오니,\n우리대학 신입생, 편입생, 재학생 모두 신청 바랍니다. [\"2025년 1학기 1차^\\n\\n국가장학금 신청기간\\n\\n_\\nAvis\\nK ee  i APE\\n와                  1\\na vat VK,\\nav\\n\\n24.11.21.) SAI\\n~12.26.[목]18시\\n\\n*반드시기간내신청\\n\\n|신첨대상\\n\\n신입생(고, 재수생 등 입왁에정지), 재화생,\\n\\n편입생, 재입화생, 복와생 등모든 대와샘\\n\\n. 재학생은 1차 신청이 웹직이며, 재학중 2회에 한해 2차 신청으로 수혜가능\\n| 신청방법\\n\\n© MADE! BE IE\\n\\n@ 곰돔인증서 @금융인즘서 @)간편인즘\\n2 한국장화재단누리집 및 모바일 앰에서신청\\n\\n# 반드시 학생 본인이 직접 신청\\nㆍ누리짐\\n\\nㆍ모바일앰\\n\\nwww.kesaf.go.kr        Q.\\n\\n쉽고 간편하게 쪽~\\n벼             갓생의 시작\\n^. 국가장학금과 함께!\\n\\n『서류제출 및 가구원 돔의기간\\n'24.11. 21.(목) 9시 ~ '25.1. 2.(목) 18시\\n0 서류제술 매상자는 몬간민므로 서류제술필수!\\n신점 2~3일후 서류제술 대상 여투들 반드시 확인이세요.\\n누리집 장학금 신정 서류제출현황\\nㆍ 모바일앰 장학금 》 서류제출\\n\\n＊ 학자금지원구간은 학생과 가구원(부모 또는 배무자)의\\n소득평가액, 재산의 소득환산액, 형제-자매수에 따른\\n\\n공제액을 반명하여 산정합니다.\\n\\n1신청문의\\n\\nKot,\\n한국장학재단 삼담센터\\n\\n1599-2000\\n\\nCy) 챙봇삼담\\n국가장확금 신청문의\\n\\n \\n\\n때\\n\\n \\n\\x0c\"]"
    },
    {
        "title": "2024학년도 국가근로장학금 동계방학 집중근로 희망근로지 신청 안내(11. 11. 9시~11. 20. 18시)",
        "url": "https://www.jj.ac.kr/jj/community/notice/janghaknotice.jsp?mode=view&article_no=443298&amp;board_wrapper=%2Fjj%2Fcommunity%2Fnotice%2Fjanghaknotice.jsp&amp;pager.offset=0&amp;board_no=1077",
        "content": "2024학년도 국가근로장학금 동계방학 집중근로 희망근로지 신청 안내(11. 11. 9시~11. 20. 18시)\n1. 희망근로지 신청 가능 대상\n- 2024학년도 2학기 국가근로장학금 1차, 2차, 3차 신청자 중 방학 중 교외근로를 희망하는 학생\n- 직전학기(2024-1) 성적 백분위 70점 이상이면서, 당해학기(2024-2) 학자금 지원구간 9분위 이하인,\n정규학기(8학기 이하, 단 건축학과는 10학기 이하) 재학생 (휴학/자퇴/제적/졸업자, 조기취업자, 산업체 위탁생 지원 제외)\n- 2024-2학기 편입생의 경우, 직전학기 성적이 없어도 장학재단 자체 선정기준에 따른 심사 결과 선발될 수 있으므로 지원 가능\n- 동계방학 집중근로 희망자는 이번 희망근로지 신청이 필수사항임\n※ 2024-2학기 현재 국가근로, 대학생 청소년교육지원사업, 보람근로 등 타 장학사업에 선발된 학생은 참여 불가\n- 교내근로는 별도 선발하지 않으며,\n현재 근로중인 학생은 선발에서 별도 통보 없이 배제함\n2. 희망근로지 신청 안내\n- 신청 방법: 한국장학재단 홈페이지 혹은 모바일\n(상단 첨부파일 매뉴얼 참고)\n- 신청 기간: 2024. 11. 11.(월) 9시 ~ 11. 20.(수) 18시\n- 근로 기간(변동 가능): 2025. 1. 1.(수) ~ 2025. 2. 28.(금) / 약 9주\n※ 방학 집중근로 프로그램의 실제 운영 기간은 교외 근로기관마다 상이 할 수 있음\n- 시급 및 최대 근로 가능 시간(변동 가능): 12,220원 / 1주 최대 40시간으로 약 9주 최대 360시간\n- 근로지는 주로 전국 각지의 공공기관 또는 준 공공기관임(시립도서관, 세무서 등)\n※ 교내근로 선발하지 않음\n3. 선발 및 근로지 배정\n- 선발 방법: 1차 한국장학재단 심사, 2차 대학 심사\n- 선발 기준(장학재단): 상단 첨부파일 참고\n- 선발 확인(변동 가능): 2024. 12. 12.(목) 18시 이후 문자 발송 예정\n4. 자체 사전교육(오리엔테이션) 실시 안내\n- 일시\n* 1차_2024. 12. 19.(목) 오후 6시 10분,\n* 2차_2024. 12. 20.(금) 오후 1시 30분\n* 둘 중 한 번 필수 참석, 오리엔테이션 참석자만 국가근로 활동 가능\n* 50~60분 소요\n- 장소: 스타센터 온누리홀\n※ 상기 운영 일정 등은 재단, 대학 학사 일정 등에 따라 변경될 수 있음\n※\n장학재단 홈페이지 및 어플 시스템 문의:\n장학재단 콜센터 1599-2290\n※\n기타 문의:\n학생지원실 063-220-2162, 2172 ['이미지 없음']"
    },
    {
        "title": "(기간 연장) 2024년도 통영시 저소득 대학생 장학금 지원대상자 선발 공고(11. 1.~11. 27. 18시)",
        "url": "https://www.jj.ac.kr/jj/community/notice/janghaknotice.jsp?mode=view&article_no=442681&amp;board_wrapper=%2Fjj%2Fcommunity%2Fnotice%2Fjanghaknotice.jsp&amp;pager.offset=0&amp;board_no=1077",
        "content": "기존 20일까지 신청 기간에서 27일까지로 연장됨\n자세한 사항 붙임 파일 참고 ['통영시 공고 제2024-9175호\\n장 공고\\n\\n2024년도 통영시 저소득 대학생 장학금 신청기간 연\\n\\ney tae 『2024년도 동영시 저소득 대학생 장학금 지원\\n\\n통영시 공고\\n데상자 선발 공고』와 관련하여 통영시 저소득 대학생 장학금 신청기간을 언장하고자\\n나음과 같이 sued\\n202444 112 18a\\n통 영 시 4\\n1. 신청기간 일정: [낭초12024. 11. .(금)~11. 20.(수)\\n\\n> [84] 2024. 11. 1.Gi)~11. 27.)\\n\\n2. 동영시 저소득 대학생 장학금 지원대상자 선발 개요\\n\\n@ 선발예정인원: 00명\\n@ 지원금액: 1인당 상한액 100만\\n\\n원\\n\\n※ 선발견과에 따라 지원인원 및 지원금액은 조정될 수 있음.\\n\\n@ 지원자격\\n가. 「국빈기초생활 보장법」 에 떠은 기초생훨수금자 및 차상위 계중 대학생으로,\\n이상(2024년 1학기 성적 기준)을 취득하고,\\n\\n나. 학업성적 평균 (학점\\n나. 관내 고등학교 졸업자로, 공고일 현재 동영시에 주빈등록상 6년\\n관내 학교를 6년 이상 다닌 자\\n\\n*현재: 당초 공고일 2024. 11. 1.일 기준\\n\\x0c', '- 2084년노 통영시 성저우수 장학금, 지역내학생 징학금,\\nUPSETS Boh 수혀자\\n\\n© AWE\\n- 학업성적이 평균 0학점 이상(2024년 1학기 성적 기준)인 자\\n@ 지원 신청\\n가. 신청기간: [낭초12024. 11. 1.(금)~11. 20.(수)\\nㄱ[번경]2024. 11. 1.(금)~11. 27.(수)\\n: 1: 방문 또는 우편 신첨\\n\\na\\n&\\noft\\n\"=\\nwh\\n\\n.편을 원칙으로 하며, 신3  3a oe 분까지 인정\\n\\nBa asad age\\n\\n \\n\\n \\n\\nWEAR                                   비 고\\n\\n8 장학금 지급신청서                            지정서식\\n(개인정보수집:이용동의서 포함)                     oor\\n\\n< 기초생활수급자 또는 차상위계층 증명서\\n\\n(9 자학증명서\\n\\n@ 성적증명서                      2024년 1학기 성적(평균 (학점 이상)\\n52h) Su oat oft Mt A Se\\n\\n6 생활기록부                     (초중고 생활기록부 중, 통명시 관나학교를\\n6년 이상 다닌 사실만 확인 가능하면 됨)\\n\\n@ 주민등록초본                           전체 주소이력 표시\\n\\n@ Sa\\n\\x0c', '@ 장학금의 지급\\n가. 지급시기: 2024년 12원 일괄\\n\\n팔 지급\\n나. 지급방법: 제출한 학생 본인 또는 보호자의 동장 게좌로 입\\n© AS 시 유의사항\\n\\n나. 제출된 일체의 서류(증빙 자료 포함\\n@ 기타사항\\n가. 선정자는 개별동보 예정\\n나. 자세한 사항은 동영시 평생학습\\n\\x0c']"
    },
    {
        "title": "2025년도 제1기 전주시 글로벌 인재양성  영어능력강화사업 장학생 선발 공고(11.11.~11.22. 18시)",
        "url": "https://www.jj.ac.kr/jj/community/notice/janghaknotice.jsp?mode=view&article_no=442392&amp;board_wrapper=%2Fjj%2Fcommunity%2Fnotice%2Fjanghaknotice.jsp&amp;pager.offset=0&amp;board_no=1077",
        "content": "자세한 사항 붙임 파일 참고 ['(재)전주인재육성재단 공고 제2024 - 21호\\n\\n2025년도 제1기 전주시 글로벌 인재양성\\n영어능력  강환사업 장 장학생 Ale 발 공고\\n\\n창조적 역량카 열린 마인드들 지년 인제로서 우리 지역 발전에 기여\\n하고 세계를 향해 꿈을 펼쳐나갈 글로별 우수인재를 발굴 유성하기 위해\\n영어능력강화사임 장학생을 아래와 간이 선발하고자 공고합니다.\\n\\n2024년 10원 23일\\n(재)전주인재육성재단 이사장\\n[1 | 사업개요\\n1. 선발인원 : 10평[국민기초생활보장수급자(치싱위게층 미포함) 1명 포함]\\n※ 제27| : 10명, 2025. 5~6월 모집예정\\n\\n2. 선발대상 : 대학생(재학생 및 휴학생)  ※ 도내대학생 7명\\n\\n※ 장학생으로 선발될 경우 2025년도 1학기를 휴학할 수 있는 학생\\n\\nMn\\n프\\n모\\nat\\n또\\nao\\nics\\n\\n \\n\\n3. 연수기간 : 2025. 1월 ~ 6원 예정  ※ 제2기 : 2025. 7월 ~ 128 Oe\\n\\n4 연수과정\\nㅇ 영어몰입 집중과정(국내)        : 2025. 1월 ~ 5원(약 5개원)\\n0 해외단기체험연수(국외)         : 2025. 6원(약 0.5개원)\\n\\nㅇ 활동보고서 작성 및 보고회(국내) : 2025. 6원(약 0.5개원)\\n5. 지원내용 : 1인당 1350만원 이내 지원\\n\\nㅇ 연수생 자부담 : 1인당 150만원(해외연수비용 중 일부\\n\\nㅇ> 국민기초생활보징수금자는 1.500만원 한도내 100% 지원\\n6. 선발방법 : 1차심사(서류), 2차심사(면접)\\n\\n7. 연수국가 : 미국\\n\\x0c', 'ㅇ 곡내연수: 어학집중고스, 자케평가, 우리지역탐방 등\\n© Baad: SEM Aa 및 때라 두어, 해외도시투어 등\\n0 황동보고 : 개인훨동보고서 및 보고회\\n\\n \\n\\n \\n\\n \\n\\n \\n\\n9. 신청자격\\nㅇ 공고일(24. 10. 23.) 기준 전주시에 주소를 두고 1년 이상 계속\\n거주하고 있는 전주시민의 자녀로서 전북특별자치도 관내 고등\\n학교를 졸업한 대학생 또는 고등학교 검정고시 졸업자격을 합\\n격한 대학생\\n0 직전학기(학기) 성적이 이상인 자\\n\\n10. 선발제한\\n\\n때\\n\\nㅇ 장기치료를 요하거나 건강상 이유 등으로 정상적인 연수활동이\\n어렵다고 판단되는 학생\\n6 학교생활 태도가 불량하여 타인에게 피해를 줄 수 있다고 판단뇌는 학생\\nㅇ 1세대 1명 신청원칙으로 지원제한\\nㅇㅇ 2024년 글로벌 인재양성 영어능력강화사업 연수생\\n11. 접수기간 : 2044 11. L(A) ~ 11 2금 18.00까지트 일-공휴일 점심시간 제외\\n\\n12. 접수원칙 : 방문접수 또는 인터넷 접수\\n\\n13. 접 수 처 :  이   인재육성재단 사무국(1.063-283-5501, 282-1813)\\n\\nㅇ 방문접수: 전주시 완산구 현무1길 31-5, 청년이음전주 5층\\n※ 본인 또는 친권자가 직접 방문신청\\n\\n- 2 -\\n\\x0c']"
    },
    {
        "title": "전북특별자치도평생교육장학진흥원 2024미래인재특기 장학생 선발 안내",
        "url": "https://www.jj.ac.kr/jj/community/notice/janghaknotice.jsp?mode=view&article_no=442383&amp;board_wrapper=%2Fjj%2Fcommunity%2Fnotice%2Fjanghaknotice.jsp&amp;pager.offset=0&amp;board_no=1077",
        "content": "자세한 사항 붙임 파일 참고 ['이미지 없음']"
    },
    {
        "title": "2025-1학기 교내장학금 신청안내(다문화, 장애인자녀, 장애대학생, 특수환경지원 장학금)",
        "url": "https://www.jj.ac.kr/jj/community/notice/janghaknotice.jsp?mode=view&article_no=446248&amp;board_wrapper=%2Fjj%2Fcommunity%2Fnotice%2Fjanghaknotice.jsp&amp;pager.offset=20&amp;board_no=1077",
        "content": "2025-1\n학기 교내장학금을 지급하고자 하오니 신입생 및 재학생은 다음 내용 확인 후 장학금 신청 바랍니다.\n1. 신청장학금: 교내장학금(다문화, 장애인자녀, 장애대학생, 특수환경지원)\n2. 신청기한: 2025. 1. 27.(월) ~ 2025. 2. 11.(화) 16:00\n3. 접 수 처: 학생회관 226호(학생지원실) 또는 e-mail(breeze@jj.ac.kr)\n4. 제출서류\n장학명\n장학금액\n자격요건\n제출서류\n다문화\n장학금\n50만원\n가. 다문화 가정의 이주민(결혼이민자) 혹은 다문화 가정의 자녀\n나. 직전학기 취득학점 12학점 이상, 평점평균 2.0 이상\n가.가족관계증명서\n나.외국인등록증,혼인관계증명서 등\n※ 국적 확인이 가능한 서류제출\n장애인자녀\n장학금\n수업료 50%\n가. 부·모의 장애 정도가 \"정도가 심한 장애인”인 경우\n나. 직전학기 취득학점12학점 이상, 평점평균 2.5 이상\n가.장학금 신청서(붙임문서 참조)\n나.가족관계증명서\n다.장애인증명서(부 또는 모)\n장애대학생\n장학금\n- 장애정도가 심한\n장애인: 200만원\n- 장애정도가 심하지\n않은 장애인: 50만원\n가. 직전학기 취득학점 관계 없음, 평점평균 2.0 이상\n가.장학금 신청서(붙임문서 참조)\n나.장애인증명서(본인)\n특수환경지원\n장학금\n- 수업료 60% 및 학업장려금 50만원\n유형 1: 아동복지시설에서 재원한 사실이 있는 자\n유형 2: 부모가 모두 사망하였거나 가출•행방불명인 자\n유형 3: 한부모가정의 부 또는 모가 교도소 수감 중인 자\n직전학기 취득학점 12학점 이상, 평점평균 2.0 이상\n가. 주민등록등본\n나. 유형별 해당 증빙서류\n5. 기타 유의사항\n가.\n신규자에 한하여 신청\n(\n입학 후\n1\n회 신청하면 매 학기 지급\n)\n나. 최종 선정자는 수업료 범위 내에서 고지서 선 감면 지급하며, 국가장학금 등의 중복지급으로 인해 장학금액 전액을 수혜받지 못하는\n경우가 발생 할 수 있음\n다. 신청자 중 장학금 지급 부적격 사유가 있는 자는 지급 불가함\n※ 문의: 063-220-2167\n붙임  장애인자녀 및 장애대학생 장학금 신청서 1\n부 ['이미지 없음']"
    },
    {
        "title": "주거안정장학금 신청(2/4 화~3/18 화) 안내",
        "url": "https://www.jj.ac.kr/jj/community/notice/janghaknotice.jsp?mode=view&article_no=446194&amp;board_wrapper=%2Fjj%2Fcommunity%2Fnotice%2Fjanghaknotice.jsp&amp;pager.offset=20&amp;board_no=1077",
        "content": "2025학년도부터 신설된 국가장학금(주거안정장학금) 신청기간을 안내하오니,\n원거리\n대학에 다니는\n기초/차상위학생\n은 신청 바랍니다.\n(신청방법은 첨부된 파일 참고!!) [\" \\n\\n25. 2. 4. (화) 9시 ~ 3. 18. (화) 18시\\n\\n \\n   \\n   \\n\\n \\n\\nAVSHS\\n원거리 대학에 다니는 기초:차상위학생(단.사입잠여대학에 한함)\\n\\n대학소재지 기준 부모님의 주소지가\\n\\n다른 교통권에 있는 경우\\n\\n#대도시권역 : 수도권 / 부산 ㆍ울산권 / 대구권 / 광주권 / 대젼권\\n{지역 : 인접(시외 경계를 맞당고 있는:시까지\\n\\nCBN Hest BAS ATA\\n\\n※상세 범위는 한국장학재단 누리집 참고\\n\\n \\n  \\n\\n솜 지원금액\\n\\n학기 중최대 월 20만원한도내\\n\\nAss\\n\\n학생이 제줄한주거안정장학금 지급 요청서 검토 후\\n\\n월 지급 한도 내에서 학생이 지출한 비용(실비)을 개별 지급\\n(학제별, 학생별 한도 내)\\n\\nft MEAS BGS! Siz\\n\\n'25. 2. 4.(화) 9시 ~ 3. 25. (Sh) 184]\\n\\n(2 서류제출 대상자는 온라인으로 서류제출 필수!\\n\\n6) 23부\\n\\n주거안점잠학금이란?\\n원거리 대학에 다니는\\n기초-차상위학생에게\\n\\n[주거관련 비용]을 지원하는 장학금\\n\\n※ 반드시 기간 내 신정\\n\\n   \\n  \\n\\nff Algor\\nLoon\\n\\nSta ashict Sele] Bt aupeletolal AV\\n*빈드시 학샘 본인이 시점 신정\\n\\n \\n\\n \\n\\n \\n\\n \\n\\n \\n\\n \\n\\n \\n\\n- 누리집                www, konaf.go.kr\\n한국장학재단   글           안정\\n콕잠학재단 장학금신정 } 신정서작성 + OES\\n+ SURRY\\nAndroid     106 '\\neae >) BB BISA > BENS\\n\\nff HAZ}\\n한국장화재탄\\n삼담센터\\n\\n1599-2000\\n\\x0c\"]"
    },
    {
        "title": "2025-1학기 국가장학금 2차 신청기간(2/4 화~3/18 화) 안내",
        "url": "https://www.jj.ac.kr/jj/community/notice/janghaknotice.jsp?mode=view&article_no=446176&amp;board_wrapper=%2Fjj%2Fcommunity%2Fnotice%2Fjanghaknotice.jsp&amp;pager.offset=20&amp;board_no=1077",
        "content": "2/4(화) 9시 ~ 3/18(화) 18시까지 국가장학금 2차 신청기간을 운영하오니,\n1차 신청 기간에 신청하지 못한 학생들은 필히 신청 바랍니다. [\"2025년 1학기[44\\n국가잠학금 신첨기간\\n'25.2.4.(화) 9시 a     |\\n\\n~3.18.(화) 18시   2 ;\\n\\n터,                     [\\n\\neer aaa |                                             :\\n\\nㅣ신청대상                             IMAM 및 가구원 동의기간\\n\\n신입고3, 재수생 통입화에절지) 편입생,  '25. 2. 4.(와) 9시 ~ '25. 5. 25.[화)78시\\nTHEI, Weta 및 1차 신첨블 봉친 재학생 ㅣ ㅣ, 포교을 대삼자는 온라인으로 서류제드 일시\\n\\n< 0646 7자전청이뢰이며, 자하 20어 새 ?시신지으 세즈 0 선철 2-3일 무 서랭페뜨 대실 며부를 반드시 확인이세요.\\n\\n \\n\\n \\n\\n바번                     누리집 NAL AAW REIS\\nㅣ신첨방법                     SSH Node tates\\n2 전지서명수탄한가지준비\\n.020인6서 6 2롤인6서 @간민요                       *＊ 하자금지원구간은 하생과가구원(부도또는배우자)이\\n소득평가액, 재산의소독환산액,험제자애수에 따른\\n< 안국잠아재탄 누리집 및 모바일앰매서 신정             공지멕을 반염하여 산정합니다\\nvwvrshoant goske\\nIalgzel\\n만피장외재탄상담벤터       a\\n1599-2000       BEE\\n\\n                                                                                                                                                                                                      \\n\\n \\n\\x0c\"]"
    },
    {
        "title": "2025학년도 1학기 국가근로장학금 (2차) 신청 안내(2. 4. 9시 ~ 3. 18. 18시)",
        "url": "https://www.jj.ac.kr/jj/community/notice/janghaknotice.jsp?mode=view&article_no=445954&amp;board_wrapper=%2Fjj%2Fcommunity%2Fnotice%2Fjanghaknotice.jsp&amp;pager.offset=20&amp;board_no=1077",
        "content": "<2025학년도 1학기 국가근로장학금 (2차) 신청 안내>\n2025학년도 1학기 국가근로장학금(2차) 학생 신청기간 및 신청 방법을 안내해드립니다.\nㅇ 국가근로장학금이란?: 지정된 근로지에서 근로하고 그에 따른 장학금을 월별 수혜\nㅇ 신청 대상:\n- 하계방학집중근로(2025년 7월~8월) 활동 희망자로,\n※ 금번 국가근로 2차 신청자는\n학기중 국가근로(2025년 3월~) 참여는 불가\n합니다.\n※\n국가근로 1차 신청자 중 하계방학집중근로에 참여를 희망하는 학생은 추후 희망근로지 신청만 진행하시면 됩니다(4~5월 중).\n금번에 국가근로 2차 신청을 다시 할 필요가 없습니다.\n- 우리 대학 정규학기 재학생 중 직전학기(2024-2) 백분위 성적이 70점 이상이며,\n- 당해학기(2025-1) 학자금지원구간(소득분위) 9분위 이하인 학생\n※ 근로장학사업 간의(국가근로 학기중, 보람근로, 대학생 청소년교육지원사업 등) 중복 참여 불가\nㅇ 신청 기간: 2025. 2. 4.(화) 09:00 ~ 3. 18.(화) 18:00\n(서류제출 및 가구원동의 기간: 2025. 2. 4.(화) 09:00 ~ 3. 25.(목) 18시\nㅇ 신청 방법:\n한국장학재단 홈페이지 또는 모바일 앱(상단 붙임문서 참고)\nㅇ근로 내용:\n- 하계방학집중근로 기간: 2025년 7월~8월 중\n- 근로지: 전국 교외 기관으로 주로 (준)공공기관(★ 교내 근로지는 미운영)\n- 시급: 12,430원(최대 근로시간은 300시간 내외로 변동 가능하며, 정확한 근로 기간 및 최대 근로 가능 시간은 추후 안내)\n- 하계방학집중근로 희망근로지 신청 필수(희망근로지 신청을 해야 신청이 최종적으로 완료됨): 2025년 4월~5월 중\n* 희망근로지 신청 기간은 한국장학재단에서 지정하며, 추후 학교 홈페이지 공지 예정\nㅇ문의\n- 한국장학재단 홈페이지, 모바일 어플 시스템 오류 등 문의 사항 1599-2290\n- 학생지원실 063-220-2162, 2172 ['이미지 없음']"
    },
    {
        "title": "중소기업 취업연계 장학사업(희망사다리1유형) 의무종사 기업기준 안내",
        "url": "https://www.jj.ac.kr/jj/community/notice/janghaknotice.jsp?mode=view&article_no=442807&amp;board_wrapper=%2Fjj%2Fcommunity%2Fnotice%2Fjanghaknotice.jsp&amp;pager.offset=20&amp;board_no=1077",
        "content": "중소기업 취업연계 장학사업 장학생은 아래 내용 필참하시기 바랍니다. ['Sidiwre                             한국장학재단                                oh\\n\\n \\n\\n \\n\\n;                   t         2\\n안내드리오니, 장학생 SA(Soil) 후 의무종사 미행 안내에 적극적인 활용을 요청 드\\n립니다\\nO ISSA SA SAIS WE\\n\\n \\n\\n구분                       인정불가 기준\\n\\n \\n\\n대기업, 중견기 멈(매출액 5.000먹원 초과), 비영리법인,\\nABER         국가-지방자치단체, 공기업-공공기관 및 자회사, 비사업자-종교단체\\n외국법인, 부모기업(부 또는 모가 대표자)\\n\\n \\n\\n \\n\\n계약방식       프리랜서, 특수형태 근로종사자(예 : 보험설계사, 택배원 등)\\n\\n \\n\\n취업지원형 | 청소년유해업소, 주점업, 사행시설 등\\n\\n \\n\\n창럽지원혈\\n\\n \\n\\n \\n\\n소속학과에 따른 진로 안내 필요\\n[유마교육] 어린미집-유치원 중 비멸리기관민\\nZI\\n\\nJ 82a 중 비명리기\\n\\n  \\n\\n기타\\n\\n \\n\\n \\n\\n \\n\\n \\n\\n \\n\\n니 의무종사 보고 방법\\n\\x0c', '빙자료를 재단 홈페이지로 보고\\n\\n \\n\\n춰 창업 기간 확인\\n\\n \\n\\n건강보험자격득실확인서\\n(또는 4대보험 가입기간 증빙서류)\\n\\n \\n\\n \\n\\n \\n\\n|업확인서)       부가가치세과세\\n\\n \\n\\n \\n\\n \\n\\n준증명원 등\\n\\n \\n\\nㅣ 기준의 주요내몽이며, 학기-사례에 따른 변동\\n\\n업무처리기준 확인이 필요함\\n\\x0c']"
    },
    {
        "title": "국가보훈장학금 국고보조금 신청 안내",
        "url": "https://www.jj.ac.kr/jj/community/notice/janghaknotice.jsp?mode=view&article_no=355705&amp;board_wrapper=%2Fjj%2Fcommunity%2Fnotice%2Fjanghaknotice.jsp&amp;pager.offset=20&amp;board_no=1077",
        "content": "국가보훈대상자 국고보조금 신청 안내\n국가유공자 등 예우 및 지원에 관한 법률에 따라, 국가유공자 본인 또는 가족에게 장학금을 지급하고 있습니다.\n대상자는 보훈처에서 해당 서류를 발급받아 학생지원실로 제출해주시기 바랍니다.\n◎ 대상자 여부 확인 및 서류 발급: 해당 지역 보훈처에 문의\n◎ 서류 안내\n구분\n제출 서류\n비고\n국가유공자 본인  또는 배우자\n교육지원대상자증명서\n3개월 이내 발급분\n국가유공자의 (손)자녀\n대학수업료등면제대상자증명서\n〃\n◎ 장학금액\n- 본인: 수업료 전액(초과학기 포함)\n- (손)자녀: 수업료 전액(정규학기 8회) - 단, 직전학기 성적 70점이상 유지하여야 계속 수혜 가능\n◎ 제출기간: 최소 당해학기 시작 1개월 전에 제출하여야 당해학기부터 적용 가능(1학기는 1월 말, 2학기는 7월 말)\n- 금번 2023-2학기는 2023. 8. 3.(목) 16시까지 제출하여야 적용가능\n- 이미 수혜받고 있는 학생은 제출하지 않아도 됨\n◎ 참고사항: 최초 1회 제출(면제여부 검토 후 계속 지급)\n◎ 제출처 및 문의: 전북 전주시 완산구 천잠로 303 학생회관 226호 학생지원실 (063-220-2982) ['이미지 없음']"
    },
    {
        "title": "★교내외 장학금 수령 계좌 inSTAR 등록 방법 안내★",
        "url": "https://www.jj.ac.kr/jj/community/notice/janghaknotice.jsp?mode=view&article_no=351217&amp;board_wrapper=%2Fjj%2Fcommunity%2Fnotice%2Fjanghaknotice.jsp&amp;pager.offset=20&amp;board_no=1077",
        "content": "교내외 장학금 수혜용 계좌 inSTAR 등록 방법 안내\n♣ 입력기간 : 상시\n♣ 입력방법\n- inSTAR → 장학/등록 → 장학관리 → 장학금 지급계좌관리\n- 지급계좌 변경 시, 재입력 후 저장시 등록완료\n♣유의사항\n- 본인 계좌 가능(부모, 형제, 친구, 지인 계좌  불가)\n- 입출금 통장 가능(청약, 적금통장, 휴면계좌 등 불가) ['Mle See\\n(1) 장학/등록 > 2) 장학 관리 (장학금 지급계좌관리) ~> 6 학생 본인 통장계좌 입격 0000엔\\n\\n간편등록!\\n\\n \\n\\notto\\n\\nCEs (eit)\\n\\n \\n\\n \\n\\n  \\n     \\n   \\n\\nith\\n\\nClee rr)        LS\\n\\nUsername\\n\\nD LyQ] Alea\\nPassword\\n\\n\" 대확에서는 국가장학금을                 장학금,             현금 지급하는 모든 형태의 장학금을 상기에 입력한 계좌를 동해 ?               ca\\n국가장학금을 포함하여 한국장학            도 가능한 이 계죄와 동일하게 관리하여 주시기 바랍니다:                                 ㅣ\\n\\nae. 기타 타인의 계좌가 0                 의 계좌이어야 하며,\\n유로 계좌를 변경해야 할 경                   } 계좌는 재학기간\\n\\n무지급계좌이력\\n\\x0c']"
    },
    {
        "title": "2024-2학기 국가근로장학금 추가신청안내(3차)_동계방학집중근로만 가능(10. 30. 9시~11. 8. 18시)",
        "url": "https://www.jj.ac.kr/jj/community/notice/janghaknotice.jsp?mode=view&article_no=441842&amp;board_wrapper=%2Fjj%2Fcommunity%2Fnotice%2Fjanghaknotice.jsp&amp;pager.offset=20&amp;board_no=1077",
        "content": "<2024학년도 2학기 국가근로장학금 추가신청안내(3차)_★방학집중근로만 가능>\n2024학년도 2학기 국가근로장학금 3차 추가신청 기간 및 신청 방법을 안내해드립니다.\nㅇ국가근로장학금이란?: 지정된 근로지에서 근로하고 그에 따른 댓가를 장학금으로 월별 수혜\nㅇ신청 기본 자격:\n- 2024-2학기 정규학기(8학기 이하)재학생 중\n- 직전학기(2024-1)백분위 성적이 70점 이상이며\n- 2024-2학기 학자금지원구간(소득분위) 9분위 이하인 학생\n* 2024-2학기 학기중 국가근로, 보람근로, 대학생 청소년교육지원사업 참여자는 참여 불가합니다.\n* 기존 국가근로 1차, 2차 신청자는 별도 이번에 다시 신청하지 않으셔도 '동계방학집중근로 희망근로지 신청(11. 11~11. 20 예정)'이 가능합니다.\nㅇ신청 기간: 2024. 10. 30.(수) 9:00 ~ 11. 8.(금) 18:00\nㅇ신청 방법: 한국장학재단 홈페이지 또는 모바일 앱(붙임문서 참고)\nㅇ근로 내용: 우리 대학\n금번 3차 추가 신청자는 동계방학집중근로 대상자로 구분(학기중 국가근로 장학생으로 선발 안함)\n- 추후 희망근로지 신청 필수\n(희망근로지 신청을 해야 신청이 최종적으로 완료됨)\n: 2024. 11. 11.(월)~11. 20.(수) 예정\n/ 추후 홈페이지 공지사항 참고\n- 희망근로지 신청자를 대상으로, 한국장학재단 및 학교 심사 후 선발된 학생이 동계방학집중근로 활동을 하게 됨\n- 동계방학집중근로 기간: 2025년 1월~2월 중\n-\n근로지: 전국 교외 기관, 주로 (준)공공기관으로\n★교내 근로지는 선발하지 않음\n- 시급: 12,220원(최대 근로시간은 320시간 내외로, 변동 가능하며 정확한 근로 기간 및 최대 근로 가능 시간은 추후 안내)\nㅇ 시스템(홈페이지, 어플) 관련 문의: 한국장학재단 1599-2290\nㅇ 학생지원실: 063-220-2162,2163 ['이미지 없음']"
    },
    {
        "title": "2025년 북한이탈청소년 장학생 선발 안내",
        "url": "https://www.jj.ac.kr/jj/community/notice/janghaknotice.jsp?mode=view&article_no=441680&amp;board_wrapper=%2Fjj%2Fcommunity%2Fnotice%2Fjanghaknotice.jsp&amp;pager.offset=20&amp;board_no=1077",
        "content": "자세한 사항 붙임 파일 참고 ['2025년 북한이탈청소년 장학생 선발안내\\n\\nㅁ 자력 요건\\n\\n1) 징부기관의 ae\\n\\n \\n\\n진학 예정인 대학생 (※\\n3) 신규학기에 타 기관(민간재탄. ‘gal 장학금 수해 대상이 아닌 학생\\n\\nㅁ 선발 절차\\n1) 선발인원 : 00령\\n3) 선발과징 : 온라인 시원 - 서류심사 - 면접심사 - 합격자 발표\\n3) 접수기간 : 2024년 10월 8일(화) ~ 10월 275   |\\nvada: my chu lal\\n\\n2 Peed soba 시윈신청서비스 접속 후 개별 신청\\nxe obsbaha AGUS UIA: http: //vel fare asanfoundation.or ke\\nㅁ 제출 서류\\n\\n) 학자금 시원구간 통시서 (한국장학재난 2034년 3학기 기준)\\n\\n \\n\\n-. 학자금 시원구간 봉시서가 없는 경우 아래서류\\n\\n모누 제출\\n\\n모누의 3038년 시방세 세목별 과세 증명서(자동차세 능 모든 세목 포한)\\n\\n2 부모 모누의 2033년 수특증명 서류\\n\\n부모가 찍장을 다닌 성우 : 3023년 근로수득위헌징수영수중(직장. 인터넷 발다)\\n\\n부모가 자영업에 종사할 정우 : 3033년 소득금액중명원(서부서. 인터넷 발급)\\n\\n  \\n\\n \\n\\n. 인터넷 발\\n\\n \\n\\n \\n\\n \\n\\x0c', '                                                                                                                                                                                                                                                                 \\n \\n\\n3) 가족관                준으로 발급 / 형제. 자매 모누 포한) 똑\\nFue\\n3) 성적증명서 : 3094년 1학기 포한 전체 성적이 나은 증명서\\n\\n(직인이 있는 성적증명서만 인정됨》\\n4) 북한이탈주민확인서\\n5) 학교(시도교수) 추왼서 : 서류심사 함격자에 한하여 제출\\n0) 보호자 동의서      : 최종 함격자에 한하여 제출\\n※ 모든 서류는 스캔하여 은라인으로 제출하며 미제출시 서류심사에서 eee,\\n\\nㅁ 장학금 지급\\n1) 장 학 금 : 학기당 300만위 생광비(연 600만원)\\n3) 시급 기간 : 매 학기마다 성적 능 장학생 자격 상심사유가 없을시\\n\\n징규학기 수료 시까시 최대 6하기 시원\\n\\n \\n\\n3) 지금 방법 :\\n\\n말, 8월 말\\n\\nof\\ncd\\n\\nㅁ 잠확생 결격 사유\\n\\n1) 전체 학업성적 평점과 찍전학기 평점이 모누 3.0에 미단하는 학생\\n\\n3) 제적. 징학 능 징계 처분을 받거나 휴학. 질병 능으로 학업을 중단한 학생\\n3) 타 기관(민간재난. 기업체) 장학금 수혜 학생\\n\\n43 기타 재단 장학사업의 취시 및 장학금 시급규징에 위배된 행위를 한 학생\\n\\n※ 장학금을 반은 해당학기를 이수하지 않을 경우, 해당학기 장학금은 반환해야 함.\\n\\n \\n\\nㅁ 장학생 의무\\n\\n \\n\\n- 재난이 고시하는 장학생 교육 및 행사 잡여 (오리엔테이션. 장학중서 수여식\\n\\n봉사캡프 능)\\n\\nㅁ 문희\\n1) 언 락 처 : 03-3010-3586. 3583 / 388010806.86001.10\\n\\n2) Ze] 4] © wv.asanfoundation.or kr\\n\\x0c']"
    },
    {
        "title": "2024년 오산교육재단 귀뚜라미 장학생 선발 안내(10. 21.~10. 23. 18시)",
        "url": "https://www.jj.ac.kr/jj/community/notice/janghaknotice.jsp?mode=view&article_no=441476&amp;board_wrapper=%2Fjj%2Fcommunity%2Fnotice%2Fjanghaknotice.jsp&amp;pager.offset=20&amp;board_no=1077",
        "content": "자세한 사항 붙임 파일 참고 ['이미지 없음']"
    },
    {
        "title": "2025 대산농촌재단 대산장학생 선발 안내(~11. 6.)",
        "url": "https://www.jj.ac.kr/jj/community/notice/janghaknotice.jsp?mode=view&article_no=441140&amp;board_wrapper=%2Fjj%2Fcommunity%2Fnotice%2Fjanghaknotice.jsp&amp;pager.offset=20&amp;board_no=1077",
        "content": "자세한 사항 붙임 파일 참고 ['이미지 없음']"
    },
    {
        "title": "(재)울산연구원 2024년 하반기 장학생 선발계획 공고(9. 30.~10. 23.)",
        "url": "https://www.jj.ac.kr/jj/community/notice/janghaknotice.jsp?mode=view&article_no=441049&amp;board_wrapper=%2Fjj%2Fcommunity%2Fnotice%2Fjanghaknotice.jsp&amp;pager.offset=20&amp;board_no=1077",
        "content": "자세한 사항 및 양식 붙임 파일 참고 ['(재)울산연구원 공고 제2024-106호\\n\\n「2024년 하반기 장학생 선발계획」공고\\n\\n우리 시의 우수한 인재를 발콜:육성하여 지역발전에 기여하고자 울산\\n획을 다음과 깥이 공고\\n\\n \\n\\n \\n\\n \\n\\n \\n\\n \\n\\nㅇ 선발분야 : 우수ㆍ희망ㆍ다자녀ㆍ생활ㆍ재능장학금 (5종)\\nㅇ 지원대상 : 초중ㆍ고ㆍ대학교 재학 생(※ 휴희생 및 정규 학제 기간 초과자 신청불가)\\n\\n0ㅇ 선발 예정인원 및 지급금액 : 331명 / 441백만원\\n\\n \\n\\n \\n\\n \\n\\n \\n\\n \\n\\n \\n\\n \\n\\n \\n\\n \\n\\n \\n\\n \\n\\n \\n\\n \\n\\n \\n\\n \\n\\n \\n\\n \\n\\n \\n\\n \\n\\n \\n\\n \\n\\n급                    a\\n\\n장학금명 | same [geo tee] oy | 신청방법\\n계                 331명      441백만원\\n\\n우수장학금                   1008      150백만원      1.500전원\\n\\n희망장학금    대학생       608      90백만원     1.500전원\\n\\n다자녀장학금                     608        90백만원      1.500전원      보이시청\\n\\n생활장학금     대학생      1018     101백만원    1.000천원    oe\\n능장학금     조종고           명         백만원          천원\\n\\n재능장학금     대학생       10명      16백만원    1.000천원\\n\\n※ 우수희망다자녀장학금의 경우 본인 부담금이 없을 경우 신청 불7\\n\\na=\\n\\n※ 생활장학금.재능장학금의 경우 본인 부담금이 없어도 신청 가능\\n스\\n수\\n\\x0c', ' \\n\\n \\n\\n \\n\\n \\n\\n \\n\\n \\n\\n \\n\\n \\n\\n \\n\\n \\n\\n \\n\\n \\n\\n때\\n\\n선발방법 및 절차\\nㅇ 선발빵법\\n\\n- 서류심사(건 기준등 이후 장학생 선발 심의위원회를 통한 대상자 확정\\n- 동점자의 경우 선받기준 우선순위에 따라 견정\\n0 절차 및 일정\\n\\n \\n\\n \\n\\n \\n\\n중복검사 및\\n격심    및              oad    ~\\n공고 및 접수         심의이뭔회 개최        최증대상자 확정\\n(9. 30. ~ 10. 23)          1g 3)           ㆍ장학금 지급\\n『                  『      (12월 중)\\n울산연구원               심의위원회 /              울산연구원\\n결생교육연구실          평생교육연구실          평생교육연구실\\n※ 진흥원 시정에 따라 일정 등은 변경될 수 있음\\n※ 장학생 선발 결과는 추후 연구원 홈페이지에 게시할 메정\\n기타사항\\n:                            SSS Sha\\n\\nㅇ 장학금 중복지원은 가능하나 선발 될 경우 장학금 3\\n능\\n\\n일체 반환되지 않으며, 미비서류 발생 시 선반과정\\nFo] ojo] Het 모든 책임은 본인에게 있음\\n\\nㅇ 경수 마감 일까지 미비한 서류가 있을 시 심사 대상에서 제외\\n\\nㅇ 장학금 수령 후 타 장학    그 rae 중복지원이 될 경우 초과분에\\n대해 연구원으로 반납해야 함\\n\\nㅇ 장학금 지급 후 서류 상 허위사실이 발견될 경우 장학생 선받이\\n취소되며 수령한 장학금 전액 반환하여야 함\\n\\n문의처\\n\\nㅇ 울산연구원 평생교육연구실 장학담당자 B) 052-266-7601\\n\\nno\\n\\n신청요건 및 선발기준 안내\\n\\n69\\n고\\n때\\nx\\natt\\nre\\nx\\n=\\n\\ntt\\n때\\n\\x0c']"
    },
    {
        "title": "2024-2학기 가족장학금 신청안내",
        "url": "https://www.jj.ac.kr/jj/community/notice/janghaknotice.jsp?mode=view&article_no=440801&amp;board_wrapper=%2Fjj%2Fcommunity%2Fnotice%2Fjanghaknotice.jsp&amp;pager.offset=20&amp;board_no=1077",
        "content": "2024-2학기 가족장학금 신청을 안내하오니, 지원 자격에 해당하는 학생은 장학금을 신청하여주시기 바랍니다.\n1. 신청 대상\n▪ 가족원 2명 이상이 본교(일반대학원 포함)에 재학 중인 학생 (부모, 형제, 자매, 남매, 배우자 등)\n▪ 성적기준: 직전학기 취득학점 12학점 이상 및 직전학기 평균평점 2.5 이상인 자\n▪ 2024-2학기 등록 후 휴학한 자 신청 가능\n2. 신청 제외 대상\n▪ 미등록자, 자퇴자, 제적자\n▪ 정규학기 초과자(이수학기 8학기 이상인 자, 건축학과는 10학기 이상인 자)\n▪ 성적기준 미달자\n3. 신청 안내\n▪ 장학금액: 가족 재학생 1인을 제외한 학부생의 수업료 40%지급\n(수업료 범위 내 타 장학금과 중복지급 가능)\n▪ 신청 기간: 2024. 10. 21.(월) ~ 11. 22.(금)\n※ 가족장학금은 매 학기 신청해야 합니다.\n▪ 신청 방법: 재학생 포털(inSTAR)→장학/등록→장학금 신청 메뉴→가족장학금 신청\n※ 장학금 신청 매뉴얼(붙임문서)참고\n▪ 제출 서류(inSTAR파일 업로드)\n가. 개인정보활용동의서1부\n나. 부 or 모 명의의 가족관계증명서1부.\n▪지급 방법: 신청학생 개인통장 지급(대출자의 경우 학자금 대출상환)\n4. 기타사항 및 문의\n▪ 「장학금지급에 관한 세칙」 제4조 1항에 따라, 접수기간 이후에는 별도 신청 없음\n▪ 063-220-2167 (학생지원실 교내장학 담당자) ['이미지 없음']"
    },
    {
        "title": "2024년도 하반기 재단법인 논산시장학회 장학생 선발 공고(~10. 25.)",
        "url": "https://www.jj.ac.kr/jj/community/notice/janghaknotice.jsp?mode=view&article_no=440732&amp;board_wrapper=%2Fjj%2Fcommunity%2Fnotice%2Fjanghaknotice.jsp&amp;pager.offset=20&amp;board_no=1077",
        "content": "자세한 사항 붙임 파일 참고 [' \\n\\n재단법인 논산시장학회 공고 제2024-02호\\n2024년도 하반기 재단법인 논산시장학회 장학생 선발 공고\\n우리 고장에 대한 애향심 및 자긍심을 고취시키고, 우리 지역발전에 기여할 수\\n있는 자랑스러운 인재 육성을 위해 2024년도 하반기 재단법인 논산시장학회\\n장학생을 선받하고자 다음과 깥이 공고합니다.\\n2024년 9월 23일\\n재단법인 논산시장학회 이사장\\n1. 선발개요\\nㅇ 신청자격 : 논산시에 1년 이상 주소를 두고 실제 거주하는 주민 또는\\n그 자녀로서 국내 정규대학교(2년제 포함)의 신입생\\n* 별도의 장학생 선받기준은 세부사항(기준일, 예외사항 등) 확인\\n@ 공고기간 : 2024년 9월 23일(월) ~ 2024년 10월 25일(금)\\n\\nofr\\n\\n홍보\\n\\n년 9월 23일(월) ~ 2024년 10월 25일(금)\\n\\n※ 시 홈페이지\\n@ 접수기간 : 2024년\\nㅇ 신청ㆍ접수방법\\n\\n- 국내 정규대학교(2년제 포함)의\\n\\n (학업장려 장학금) 개별 신청\\n\\n- 논산시 관내 대학교(2년제 포함)의 신입생\\n\\n신입\\n\\n생\\n\\n* (지역대학진학 장학금) 대학교\\n\\n※ 신입생 장학금은 상반기 미신청\\n\\n학장(총장) 추전\\n자에 한해서 신청 가능\\n\\n@ 장학금 지급 : 2024년 11월 중순\\nㅇㅇ 장학금 신청 방법\\n\\n- 공고문에 첨부된 신청서 및 기타 구비서류 지참하여 해당 접수처에 방문 신청\\nㅇ@ 문의처 : 논산시청 인구청년교육과 교육지원팀(041-746-5773)\\n\\x0c', '2. 세부사항\\n| 학업장려 장학금\\n\\n \\n\\n \\n\\n \\n\\n \\n\\n \\n\\n \\n\\n \\n\\noO 선발기준\\n- 2024년도 국내 정규대학교(2년제 전문대 포함) 신입\\n- 2005년 1월 1일 이후  도보. “12 31. 기준\\n※ 단, 미성년으로 고교진학 후 2004년도 「초.중등교육법」제2조제3항 고등학교\\n교육시설를 졸업한 경우 예외로 선\\n- 학생 본인, 부, 모 증 어느 한 명이라도\\n논산시에 제속하여 1년 이상2023년 9월 24일 ㅇ\\n※ 「고등교육법」 제2조 중 국내의 대학, 산업대학,\\n제외대상\\nㅁ 원격대학(사이버대학, 방송통신대학), 대학원대학\\n=» 평생교육법에 의한 학점은행제 교육원 및\\n 생활비를 지원받는 특수학교(경찰대. 육해-공군시\\n\\n※ 생애 첫1회만 지급 가능\\n\\n  \\n\\n \\n\\n \\n\\n \\n\\n \\n\\n \\n\\n상반기 논산시장학회 장학금 수령자 제외\\n《 기타 특수한 경우 재단법인 논산시장학회 이사회를 통해 결정\\noO 지원내용 : 1인 1벅만원\\nㅇ 신청자:지원대상자본인또는부 모\\nㅇ 신청접수: 방문 접수 또는 우편 접수(등기우편만 가능)\\n- 신청기간 : 2024. 9. 23.(월) 09:00 ~ 10. 25.(금) 18:00 / 32일간\\n- 점 수 처 : 논산시청 인구청년교육과 ras) a lod 146-5779)\\n(우편번호 32987, 수신처 충남 논산시 시민로210번길 9, 논산시청\\n인구청년교육과 논산장학회 담당자)\\n※ 등기우편 접수의 경우 2024. 10. 25.(금) 우체국 소인분까지 인정\\nOo THAT\\n02 장학금 신청서 및 개인정보 수집 및 활용 동의서\\n@ 부 또는 모 신청 시 지원 대상자 본인과 같은 세대일 경우 : 주민등록표 등본\\n(9) 논산지에 1년 이상 주소를 둔 지원 대상자 본이이 신청하는 정우 : 주뭔등록표 초본\\n14 지원 대상자 본인과 부 또는 모가 주소가 다른 정우 : 조본, 가족관계증명서\\n※ 2 9 8 등초보은 주민등목상는산시 거주자 기준으로 주소 벤등시항 전체 포함 발급\\n(9 입출금 통장 사본(신입생 본인)\\n6@ 대학교 재학증명서(정부24, 재학 중인 대학교에서 발급 가능)\\n00 2024년도 고등학교 졸업증명서(2004년 12월 31일 이전 출생자만 해당)\\n\\x0c']"
    },
    {
        "title": "2024-2학기 대학생 청소년교육지원사업 신규장학생 활동 안내",
        "url": "https://www.jj.ac.kr/jj/community/notice/janghaknotice.jsp?mode=view&article_no=440623&amp;board_wrapper=%2Fjj%2Fcommunity%2Fnotice%2Fjanghaknotice.jsp&amp;pager.offset=20&amp;board_no=1077",
        "content": "2024-2학기 대학생 청소년교육지원사업 신규장학생 활동 안내\n1. 선발 결과 확인\n-한국장학재단→메뉴→인재육성→대학생청소년교육지원사업→서약서/온라인사전교육 메뉴에서 사전교육 강의가 조회되는 경우 선발된 것임\n2. 기본 사항\n- 활동 내용: 초중등학생 학습 보충 지도, 상담(학교생활, 교우관계, 진로 등) 및 피드백 등 지원\n※ 이외에 활동 기관, 대학, 멘토가 멘티에게 필요한 활동이라고 동의한 경우 활동으로 인정. 단, 활동기관 업무보조(단순노무) 등의 활동은 인정하지 않음\n- 활동 장소: 대면 멘토링의 경우 멘티 소속기관(멘토, 기관, 대학 간 협의를 통하여 활동 장소 변경 가능하나 공공시설로 한함)\n- 활동 기간: 2024년 10월 아래[4번 멘토링 시작 전 활동 사항] 완료 후 ~\n2025년 2월 말까지(3월은 활동 불가, 예산 소진 상황에 따라 조기 종료될 수 있음)\n- 시급: 12,220원\n- 장학금 지급일: 익월 15일 경(예: 4월 활동분은 5월 15일 경 지급)\n- 활동 가능 최대 시간: 1일 8시간 / 1주 20시간(학기중), 40시간(방학중) / 2024-2학기(동계 방학 포함) 최대 400시간\n3. 유의 사항\n- 아래 [4번 멘토링 시작 전 활동 사항] 완료 전의 활동에 대해서는 장학금 지급 불가\n- 휴학/자퇴 시, 학적 변동 신청일 전날까지 근무 가능, 졸업/제적의 경우 졸업일(제적일) 전날까지 근무 가능(우리 대학 기준)\n- 학사 징계를 받은 경우 활동 불가\n- 조기취업자*, 초과학기생, 산업체 위탁생 등은 활동 불가하므로 취업계를 신청할 경우, 학생지원실 담당자에게 통\n보\n*조기취업자: 재직증명서 및 4대 보험 가입내역이 확인되는 경우(단, 일용직/아르바이트/체험형인턴은 조기 취업자에 해당되지 않음)\n- 이해관계 회피의무:\n근로지 직원과 가족관계나 이해관계가 있는 경우 근로할 수 없으며, 한국장학재단 모니터링 시 적발 및 제재될 수 있음\n- 타 장학사업(국가근로, 보람근로 등)과 중복 참여 불가\n- 활동 기관에서 별도의 금전적 지원 또는 사회봉사인증 등을 받으며 활동 불가\n- 멘토링 중, 해외여행/군복무 등의 계획이 있다면\n근로중지사전신고 실시\n(가이드북 197P 참고)\n- 부정근로를 금지하며(허위근로/대리근로/대체근로), 위반 시에는 장학금 환수, 사업 참여가 제한됨\n4. 멘토링 시작 전 활동 사항(다음 순서대로 진행)\n1) 활동 기관 발굴\n(첨부파일 멘토 가이드북 PART6 활동가능기관 찾기 참고)\n- 활동 가능 기관: 전국 초중등학교(특수학교 포함), 지역아동센터, 학교 밖 청소년지원센터, VMS/1365(정부인증포털) 등록시설, 청소년방과후아카데미 운영시설(한국청소년활동진흥원 인증), 한국장학재단으로 제한\n※ 아동권리보장원(www.icareinfo.go.kr), 보건복지부 사회복지자원봉사인증관리센터VMS(www.vms.or.kr), 행정안전부 자원봉사포털1365(www.1365.go.kr), 청소년방과후아카데미(www.youth.go.kr/yaca/index.do)에 등록된 시설이어야 함\n- 활동은 2개 기관에서 병행 가능\n※ 어린이집, 유치원, 노인복지시설 등 활동 불가\n2) 활동계획서 작성 및 제출\n- (공통) 활동을 원하는 기관 담당자와 업무스케쥴을 협의하여 활동 계획서 작성(첨부파일 양식), 2024-2학기 학업시간표(인스타에서 확인되는 정규시간표)와 함께 제출\n- 제출 방법 및 기한: 학생회관 2층 226호 학생지원실 방문 제출 / 9. 30.(월)까지\n(학교는 제출 서류를 기반으로 기관과 학생을 한국장학재단 시스템상에서 매칭, 매칭에는 2~3일 소요 예상, 매칭이 완료되면 출근부 어플에 기관 정보 확인됨)\n- (해당 시) 발굴 기관이 기존에 대학생 청소년교육지원사업을 참여하지 않은 신규 기관일 때,\n기관 최초 등록 시 활동기관은 세금 및 사회보험의 체납 사실이 없는 것에 대한 증빙으로써 사업장 명의의 국세, 지방세, 4대보험 완납증명서 제출\n※ 개인사업자인 경우 대표자 명의의 국세, 지방세 완납증명서 가능(단, 4대보험 완납증명서는 반드시 사업장 명의로 제출)\n※ 정부, 지자체, 초중고등학교, 학교법인, 공공기관은 제출 대상에서 제외\n※ 지역아동센터의 경우 4대 보험 완납증명서, 시·군·구청에서 교부한 신고증 제출 가능\n3) (기관-학생 매칭 완료가 되어 출근부 어플에서 기관이 확인 된 후) 학업시간표 등록, 업무스케쥴 입력\n(방법 첨부파일 가이드북 참고 업무스케줄 168P, 217P / 학업시간표 156P, 205P )\n<학업시간표 입력>\n- 학업시간표는 우리 대학 시스템에 등록된 정규 시간표를 보이는 그대로 입력해야 함. '진로탐색/세미나' 시간도 그대로 입력해야 하고 그 시간에는 멘토링 불가함. 온라인 수업 중 시간표가 정해져 있는 수업도 그대로 입력해야 함 (학업시간표를 정확히 입력하지 않고 멘토링한 경우, 한국장학재단 모니터링 시 부정근로로 적발됨)\n- 9. 30.(월) 자정까지 입력\n- 부득이하게 근로 중간에 시간표를 정정해야 할 경우 담당자에게 연락\n- 학업시간표와 중복된 시간에 멘토링이 불가하며, 일시적인 휴강 시간에 근로 불가(학업시간표와 중복되어 인정되지 않음)\n<업무스케쥴 입력>\n- 업무스케쥴은 작성한 활동계획서를 기반으로 입력(입력된 업무스케쥴로 출근부가 활성화 됨)\n-활동 시작 전날까지 입력해야 함\n4) 한국장학재단 온라인 사전교육(총 6차시) 이수 및 서약서 제출\n(첨부파일 가이드북 173P 참고 )\n- 한국장학재단 홈페이지 로그인 후 진행\n- 활동 시작 전날까지 수료 완료해야 함\n------------------------------------------------------\n위 단계까지 다 완료된 이후 활동만 인정됨, 그 이전 활동 인정 불가\n9월은 근로 불가하고, 10월부터 가능\n5. 멘토링 시작\n- 출근부 입력은 활동 즉시 입력이 원칙\n임(출근부 입력 방법 가이드북 180, 217P 참고)\n- 부득이하게(출근부 앱 오류 등) 기한 내 출근부 입력을 못하였거나 수정이 필요할 시, 활동 기관 담당자에게 입력 또는 수정 요청\n※ 단, 기관 담당자의 수정 입력이 잦을 경우, 한국장학재단 부정근로 모니터링 시 의심사례로 적발될 수 있음\n- 기관 및 멘티와 협의하여\n온라인으로 멘토링\n할 경우(ZOOM, 스카이프, 행아웃, 네이버밴드 라이브, 카카오톡 페이스톡 등 활용): 출근부 작성 시\n온라인 멘토링 증빙 양식\n(첨부파일 참고)에 멘토링 일자/시작시간/종료시간을 포함한 화면 캡처본을 출근부에 필수로 첨부\n※ 화면 캡처 상에 찍힌 시작시간~종료 시간만 근로 시간으로 인정되므로, 출근부 활동 시간 입력 시 캡처 상의 시간으로 입력해야 함\n- 활동 기관 담당자는 출근부를 매월 말일 또는 익월 초일까지 한국장학재단 시스템에서 대학 제출 처리해야 함\n(한 개의 기관에서라도 대학 제출이 늦어질 경우, 전체 학생 장학금 지급이 늦어지게 됨. 활동기관 담당자에게 안내 필요)\n- 최초 멘토링 누적 시간 40시간 이상이 되는 경우, 활동 기관 담당자-멘토 학생 상호평가 실시 필수(가이드북 195P 참고)\n6. 우리 대학 자체 사전교육(필참)\n- 일시: 2024. 9. 23.(월) 오후 6시 10분\n- 장소: 학생회관 2층 한국어교육센터 231호 강의실\n[문의]한국장학재단 홈페이지 및 출근부 어플 관련: 1599-2000 ['이미지 없음']"
    },
    {
        "title": "(재)익산사랑장학재단 2024학년도 2학기 다다익산 장학생 선발 공고(9. 20.~9. 26. 18시)",
        "url": "https://www.jj.ac.kr/jj/community/notice/janghaknotice.jsp?mode=view&article_no=440494&amp;board_wrapper=%2Fjj%2Fcommunity%2Fnotice%2Fjanghaknotice.jsp&amp;pager.offset=20&amp;board_no=1077",
        "content": "자세한 사항 붙임 파일 참고 ['(제익산사랑장학재단 공고 제2024-호\\n\\n우리지역 발전에 기여할 미래인재 발굴ㆍ육성ㆍ지원을 위한 024년도 3학기\\n다다익산 장학생 선받을 아래와 같이 공고합니다.\\n\\n2024년 9월 13일\\n재단벌인 익산사랑장학재단 이사장\\n\\n2024년도 2학기 다다익산 장학생 선발 공고\\na Al 4! WH\\n\\n선발대상 : 5자녀 이상 가구 대학 재학생(휴학생 제외)\\n2. 선발인원 : 75명(* 예산상황 등에 따라 변동될 수 있음)\\n3. 지  급 aq: + 121 학기당 100만원 * 학기별 신청\\neae 개별접수(1학기 다다익산 장학금 신청과 무관)\\n\\nuae\\n\\n \\n\\n \\n\\n \\n\\n \\n\\n \\n\\n \\n\\n \\n\\n \\n\\n \\n\\n \\n\\n \\n\\n \\n\\n \\n\\n \\n\\n \\n\\n1. 주소\\n대상          기 준                        요 건\\nBy peep soy | Soe 기준 본인 또는 보호사(부모 중1인)주수가 년 이상\\n익산시로 되어 있는 자\\n.                     공고일 기준 본인 또는 보호자(부모 줄1인)주소가 2년 이상\\n한생     관외 고등학교 졸업생     그\\nWere    과외 고등학교      익산시로 되어 있는 자\\n교내 nue   ae 기준 학생 본인의 주소가 6개월 이상 익산시로 되어\\n2.44\\n대 상                         기       준\\n- 2024년 1학기 평점 평균 2.5학점 이상(복혁생은 직전학기 성적\\n학생\\n으으으 | |: , 기당학기 취득학점 12하점 이상(단, 4하년은 잔여 학점 이수자)\\n\\n \\n\\n \\n\\n \\n\\n \\n\\x0c']"
    },
    {
        "title": "인천인재평생교육진흥원 2024년 하반기 장학생 선발 안내(9. 12.~10. 6. 23시)",
        "url": "https://www.jj.ac.kr/jj/community/notice/janghaknotice.jsp?mode=view&article_no=440187&amp;board_wrapper=%2Fjj%2Fcommunity%2Fnotice%2Fjanghaknotice.jsp&amp;pager.offset=20&amp;board_no=1077",
        "content": "자세한 사항 붙임 파일 참고 ['이미지 없음']"
    },
    {
        "title": "2024년 (재)고속도로장학재단 고속도로 장학생 선발 안내(~10. 11.)",
        "url": "https://www.jj.ac.kr/jj/community/notice/janghaknotice.jsp?mode=view&article_no=440186&amp;board_wrapper=%2Fjj%2Fcommunity%2Fnotice%2Fjanghaknotice.jsp&amp;pager.offset=20&amp;board_no=1077",
        "content": "[' \\n\\n;\\n\\n2024년 고속도로 장학생 선발 안내문\\n\\n(재;고촉도로장학재단은 고속도로 사고 피해가족이 경제적 이유로 학업을 포기하지\\n않도록 지원하기 위하여 지난 1996년 한국도로공사에서 설립한 재단법인입니다.\\n2044 고속도로 장학생」을 다음과 같이 선발하오니 해당되는 분은 신청하여 주시기\\n바랍니다.\\n\\n-다 음\\n1. 신청자격\\n\\nㅇ 고속도로 사고(교통사고 및 건설ㆍ유지관리 만전사고로 인하여 사!\\n장매의 정도가 심\\n\\noh\\na Woieioase 장애인복지법 wos 판정된 자 뜻\\n\\n \\n\\n0 인원 : 대학생ㆍ고등학생 0600명, 중학생 이하 00명\\n\\n※ 서류 시사 후 심의위원회 의결을 거쳐 선발(인원 조과 시 관련 기준에 따라 선발]\\n\\n3. 장학금 지급액\\n대학생      고등학생\\nFE Wz |\\n_    차상위\\n금액 soot\\n* 잠학금은\\n\\n5 2888 | oes og\\n차상위  밀반 | (신생아 영유매\\n\\n \\n\\n \\n\\n \\n\\n \\n\\n \\n\\n300만원 | 200만뭔 | 200만원\\n\\n1가구 1민 신청 원칙, 단, 기초생활수급자:ㆍ차성위계춤의 경우 1가:\\n4. 신청서 제출\\n\\n(재)고속도로장학재단\\n(13595) 경기도 성남시\\n\\n홈페이지(*%4\\\\.151.0(400\\n분당구 황새물로200번길 34, 1101호\\n\\n0 접수기간 : 2024. 9. 9(월) ~ 10. 11(큼) ㆍ우편전수 시 접수 마감일 소인문끼지 유효\\n\\x0c', '부\\n\\nyd\\n\\n줄\\n\\n|서 함께 제\\n\\n이용 동의\\n\\n드\\n\\n0 기타 사실\\n\\n[해당자]\\n\\n5. 제출 서류\\n\\n4\\nx\\n\\n따\\n\\n때\\n\\n°\\n\\n1}\\n\\n회\\n\\n[재단 er 031-712-8942 / www.hsf.or. kr\\n\\nAb BEA w 054-811-1341~2\\n\\n3 OOF MAKeermel yay, CHAE Measles\\nys\\n\\n대상자 확정(장확재단 이사화\\n\\n: 적\\n장학금 지급\\n한국도로공사\\n\\n국도로:\\n\\no 108\\none\\n0 28\\n\\n°\\n\\x0c']"
    },
    {
        "title": "서울특별시 은평구민장학재단 장학생 선발 공고(9. 23~10.7 18시)",
        "url": "https://www.jj.ac.kr/jj/community/notice/janghaknotice.jsp?mode=view&article_no=440135&amp;board_wrapper=%2Fjj%2Fcommunity%2Fnotice%2Fjanghaknotice.jsp&amp;pager.offset=20&amp;board_no=1077",
        "content": "자세한 사항 붙임 파일 참고 ['은평구민장학재단 공고 제2024-10호\\n\\n \\n\\n2024. 하반기 은평구민 장학생 선발 공고\\n\\n은평구 교육환경 개선과 우수한 인재를 발굴ㆍ육성하기 위하여 설립된\\n(재)은평구민장학재단에서 운영 규정 제5조에 의거 『2024. 하반기 은평\\n구민 장학생 선발 계획』 을 다음과 깥이 공고함니다.\\n2024년 9월 6일 Po\\n재단법인 은평구민장학재단 이사장\\n1. 재단 안내\\nㅇ 명 청 : 재단법인 은평구민장학재단\\nㅇ이사장:이호종\\nOM 처 ： 서울브볼시 은평구 은평로 195(복빈농) 은펑구청 본관 3충 시민교과\\nㅇ 연락처: 02- 351- 8512\\n\\n2. 장학생 선발요강\\n\\nㅇ 선발분야 : 3개 분야(일반, 특기, 나비)\\n\\nㅇ 선발인원 : 0ㅇ명\\n\\nㅇ 신청거간 : 2024. 9. 23.(월) ~ 10. 7.(원) 18:00까지\\n(주말, 공휴일 및 접심시간 12:00~13:00 제외)\\n\\nㅇ 신청자격 : 공고일 현재 은평구에 9년 이상 계속 거주(주민등록기준)하고\\n있는 초ㆍ증ㆍ고ㆍ대학생\\n\\n0 신청방법 : 등기우편 및 방문 접수\\n\\n- 추천권자(학교장 등)의 직인을 받은 신청서 및 기타 제출서류 우편 및\\n\\n방문 접수\\n\\x0c']"
    },
    {
        "title": "(재)춘천시민장학재단 2024년도 하반기 봄내장학생 선발공고(9. 19.~9. 27.)",
        "url": "https://www.jj.ac.kr/jj/community/notice/janghaknotice.jsp?mode=view&article_no=440055&amp;board_wrapper=%2Fjj%2Fcommunity%2Fnotice%2Fjanghaknotice.jsp&amp;pager.offset=20&amp;board_no=1077",
        "content": "자세한 사항 붙임 파일 참고 ['(재)춘천시민장학재단 공고 제2024-13호\\n\\n미재]준천시민장학재단』\\n  2024년도 하반기 봄내장학\\n그\\n선발공고\\n지역 우수인재를 발굴ㆍ육성하고 내 고장에 대한 애향심과 자긍심 고취를\\n위한 (재)춘천시민장학재단 2024년도 하반기\\n\\n봄내장학생을 선발하고자 다음과\\n같이 공고합니다.\\n\\n2024년 9월 6일\\n\\n재단법인춘천시민장학재단이사\\n\\n \\n\\nEvia\\n\\n|\\n\\nㅇ 신청기간: 2024. 9. 19.(복) ~ 9. 27.(금) [8일간]\\n\\nㅇ 접수처:\\n\\n애향장학금 신청 = 주소지 읍면동 행정복지센터\\n\\n성적우수특기주소이전원격대학 장학금 신청 = 장확재댄식주3 준천노사3사 본란 33\\n※ 방문 및 우편(능기)점수 (단, 우편은 접수마감일까지 도착분만 인정)\\n\\n신청서식: 재단 홈페이지01[0://(007000086.0.10) 또는 시 홈페이지(춘천시\\n\\n(chuncheon.go.kr) 내려받기 가능\\n(재단 홈페이지: 열런마당-> 공지사항 게시판-> 2024년도 하반기 장학생 선발공고)\\n(시청 홈페이자 행정정보-> 알림정보-> 타키판고시/공고 > 2024년노 하반기 장학생 선발공고\\n\\x0c', '2\\n\\nth 50\\n\\n금:\\n\\n}장하\\n2024. 11월 중(선발된 자 개별연락)\\n\\n3]\\n\\nla che\\n\\n춘천시민장학재단 장학금 지원 선발기준에 의함\\n\\n수여식 당일 교부(일시ㆍ\\n\\n* 우\\n\\n서:\\n\\n증\\n\\n©\\n공통\\n\\n*1가구에서 2명 0\\nㆍ 분야별 중복지\\n\\nㅇ 장 학 금: 고등학생 50만 원, 대학생 최대 100만 원\\nSs\\n\\nㅇ 선발결과 및 지급시기:\\nㅇ 유의사항: 타장학금과\\n\\nㅇ 선발방법:\\nㅇ 장학\\n\\n)\\n\\n『 예외적으로 가능\\n\\n형만\\n\\n야\\n\\n기본지\\n\\nㆍ 직전학\\n\\na\\na\\n\\n|는 금액만 지\\n\\n히\\n\\n)\\n\\n글:\\n\\n경우\\n\\n의\\n\\n제, 시간제\\n경우, 실제 납부액에 해당\\n\\n받는 경우, 실\\n미응시자.\\n\\n받는\\n, 수능시험\\n\\n지원\\n준)\\n\\n면제 또는\\n험 성적(9등급 기\\n\\n수학능력시\\n\\n \\n\\n \\n\\n학수\\n\\n \\n\\n대\\n\\x0c']"
    },
    {
        "title": "(재)포항시장학회 2024년도 대학교 장학생 선발 안내(~9. 25. 18시)",
        "url": "https://www.jj.ac.kr/jj/community/notice/janghaknotice.jsp?mode=view&article_no=439998&amp;board_wrapper=%2Fjj%2Fcommunity%2Fnotice%2Fjanghaknotice.jsp&amp;pager.offset=20&amp;board_no=1077",
        "content": "자세한 사항 재단 홈페이지 참고 [' \\n\\n[재]포항시장학회 2024년도 대학교 장학생 선발 계획\\n\\n=    c=\\n  장확생 선발개요\\n1. 선 발 연 원 : 420명\\n2. 장 학 금 액 : 840백만원\\n* 1인당 200만원, 당해학기 등록금 법위 내 지원\\n3. 신청자격 및 요건(아래의 요건을 모두 충족해야 함)\\n0 신청자격\\n\\nㆍ 선발 공고일 현재\\n\\n \\n\\n \\n \\n\\n포항시에 주민\\n\\n \\n\\nㆍ 2024년도 2학기 한국장하재단 하자금 지원구간 통지를 받은 자\\nㅇ 성적기준 : 직진 학기 성적 평균 25점 이상 인 AAS 만점 기준)\\n\\n※ 문*예*가 득기장학금 , 곰두리(장애)장학급은 성적기준 없음\\n\\n6 지원제외\\n* 공고인 현재 휴하 및 되학 동 징계 처문을 받은 자\\n* 부보가 직장\\n\\n \\n\\n* 2학기 등록급 전액 면제자 및 본인 부담금 50만원 미만인 자\\nㆍ 서울 포항학사 입사생\\nㆍ 학점은행제, 직업학교 재학생\\n때 져수방법\\nㅇ 접수방법 : 재단 홈페이지 온라인 저수\\n- 기   간 : 2004. 8. 27(화) 09:00 ~ 2024. 9. 25(수) 1800\\nOF    의 : (재)포항시장학회 (줄 054-270-5757~8)\\n\\n※ 자세한 사항은 (재)포항시장학회 홈페이지(4\\\\\\\\|)1911109) 공지사항 참조\\n\\x0c']"
    },
    {
        "title": "(참고)국가장학금 가구원 동의 절차 안내",
        "url": "https://www.jj.ac.kr/jj/community/notice/janghaknotice.jsp?mode=view&article_no=439707&amp;board_wrapper=%2Fjj%2Fcommunity%2Fnotice%2Fjanghaknotice.jsp&amp;pager.offset=20&amp;board_no=1077",
        "content": "첨부와 같이 국가장학금 가구원 동의 절차를 안내하오니,\n아직 가구원 동의를 완료하지 않은 학생들은 참고하여 완료 바랍니다.\n(절차가 완료되어야 소득구간 산정 및 승인절차가 진행됩니다) [' \\n\\n가구원 확인은 이렇게 진행됩니다!\\n\\n@ 가구원 확인이란? 학생이 신청 시 입력한 동의 대상 가구원을 행정정보공동이용 주민등록전산정보 및\\n대법원 가족관계등록전산정보름 통해 실제 가족관계 확인(1~3일 소요)\\n\\n@ 다만 전산정보로 확인되지 않는 경우, 서류제술이 진행되며 서류제술대상자에게 문자 통지\\n\\nMEA ASAE MEAL      메뉴메서 반드시 서류 제총 월요\\n\\n가구원 모두의 동의가 완료되지 않으면 해당 학기 학자금 지원구간 산정이 불가합니다!\\n\\n# 동의 대상 가구원 범위 (신청 대학생의 결혼 유무에 따라 상이)\\n- (미혼) 학생 + 부모 모두, (기혼) 학생 + 배우자\\n 가구은 부일관계 단절 는 돋의 불가 시. 제외 심사을 봉해 농의대상 가구원저 외\\n\\n~ 확샘 본인이 기추섬왼수금사 닛 차삼의계층 자격은 것으 확인된 경우 가구원의 섬로 제공 동의 생약 가능\\n\\n가구원동의는온라인 동의또는 오프라인 동의로 가능합니다!\\n\\n* 온라인:홈페이지 또는 모바일 앤2 접속 = 가구원(부모님 또는 배우자;의 전자서명으로 동의\\n1) BOA] +: http://www.kosaf.go.kr 2) 2 UP 2! OY 284:: https://mo.kosaf go. kr/apps\\n\\n6 오프라인 : 입원. 고령. 농어촌거주, 장애 등 온라인 동의 불가 시 상담센터 문의 후 오프라인 동의 진행\\n\\nㆍ 오프라인 동의의 경우 상담센터로 문의 후 진행되므로, 가구원 동의 처리기간이 길어질 수 있음\\n\\n* 전자서명: 공동인\\n\\n인즘서 또\\n\\n* 한국장학재단 상담센터 1599-2000\\n\\nAG atk\\n\\nPY! FIL 및 기구윤 돔의가 왼료되지 많는 경우 학자금 지윤\\n최신화 소정 현!10영업원] 및 미비서큐제중기한영업일 이\\n\\x0c']"
    },
    {
        "title": "(신청기간 연장)2024년 2학기 고졸 후학습자 장학사업(희망사다리 Ⅱ유형) 신규장학생 신청 안내(9. 2. 9시~9. 27. 18시)",
        "url": "https://www.jj.ac.kr/jj/community/notice/janghaknotice.jsp?mode=view&article_no=439374&amp;board_wrapper=%2Fjj%2Fcommunity%2Fnotice%2Fjanghaknotice.jsp&amp;pager.offset=20&amp;board_no=1077",
        "content": "2024년 2학기 고졸 후학습자 장학사업(희망사다리 Ⅱ유형) 신규장학생 신청 안내\n중소·중견기업\n재직자,\n중소·중견기업\n창업자\n라면 등록금\n전액\n지원\n☞ 현재\n재직\n중인 대학생에게\n등록금\n을 지원하는 고졸 후학습자 장학금\n★2024년 2학기 신규장학생 약 3,400명 내외 선발 예정\n※ 이전 동일학기 평균 지원 규모 대비 약 1,500명(1.6배) 확대 선발 예정\n※ 신청인원이 선발인원을 초과한 경우, 업무처리기준에 명시된 심사절차를 통해 고득점자 순으로 선발 진행\n안녕하세요, 한국장학재단입니다.\n2024년 2학기 고졸 후학습자 장학사업(희망사다리 Ⅱ유형) 신규장학생 신청접수 기간을 아래와 같이 운영하고자 하오니, 내용을 참고하시어 신청기간 내에 신청을 완료해주시기 바랍니다.\nㅁ 2024년 2학기 신규장학생 신청기간:\n'24. 9. 2.(월) 09시\n~ 9. 27.(금) 18시\n'\n(신청 기간 연장됨)\n*\n첨부된 매뉴얼 필독\n후 한국장학재단 홈페이지 통해 신청\n*\n신청정보 허위기재 및 오기재는 자동 탈락\n처리되며, 장학금 지급 후에 해당 사실이 확인된 경우에도 기수혜 장학금 전액 환수 처리됨에 유의\nㅁ 장학금 개요\nㅇ 지원자격\n- 다음의 조건을 모두 충족한 대학생(재학생)\n① 대한민국 국적자로\n최종학력이 고졸인 자\n※ 전문학사 취득자가 전공심화과정 및 4년제 대학에 신편입하는 경우, ‘전문학사 취득 전’ 산업체 재직기간(군 복무기간 미포함) 2년을 별도로 충족하면 장학금 지원 가능 <증빙서류 제출 필요>\n②\n직전학기 성적이 백분위 70점 이상인 자\n③\n2024년 7월 1일 기준 재직기간이 2년 이상인 자(\n단\n,\n심사기준일 당시\n중소\n·\n중견기업 재직자는\n1\n년이상\n)\n※ 고용보험 가입정보 기준으로 산정하며 이전 재직 기업 유형 및 규모는 무관. 군 복무기간을 포함하되, 재직 경력이 최소 6개월(180일) 이상이어야 함\n④\n2024년 7월 1일 기준 지원 대상 기업에 재직 중인 자\n※ 「중소기업법」 및 「중견기업법」에 따른 중소·중견기업과 기업신용조회사에서 대기업으로 분류한 기업, 비영리법인, 비사업자까지 포함(기업유형 및 규모에 따라 차등지원).\n★ 단, 업무처리기준 상 \"재직 인정 제외 기업\"(부모기업, 공공기관, 국가기관 및 지방자치단체, 법인이 아닌 종교단체 등 업무처리기준에 적시된 재직 인정 제외 기업)은 지원 불가하며 장학생 선발 이후 해당 사실 확인 시에도 기수혜 장학금 전액 환수 처리\n▶ 사업 예산 범위 내에서 연령, 재직기관, 출신고교, 기업재직기간에 따라 차등 배점하여\n총점이 높은 순으로 장학생 선발(상세내용은 첨부된 FAQ 참조)\n★ 모든 요건을 다 충족하더도, 선발배점에 따라 선발이 불가능 할 수 있음 ★\n본인이 가점을 받을 수 있는 서류를 필히 확인하여 신청기간과 이의신청기간에 제출해야 하며\n★ 기간 내에 해당 서류 미제출로 인하여 선발배점 후순위에 따른 탈락은 절대 구제 불가\nㅇ 지원사항\n수혜횟수 범위 내 정규학기 및 초과학기 등록금 지원하되, 현 재직기업 유형 및 규모에 따라 차등 지원\n- 중소·중견기업: 등록금 필수경비 전액\n- 대기업, 비영리기관(비영리법인, 비사업자): 등록금 필수경비 50%\n※ '24년도 2학기 선발된 장학생은 향후 별도 신청 없이 계속장학생으로 심사 진행되며, 계속장학생 심사요건을 매 학기 충족 시 등록금 지원. 계속장학생 심사 관련 사항은 업무처리기준 참고\n※ 단, 장학금 지급 시점(11월 중 예상)에 이미 타 장학금으로 전액 수혜한 경우, 고졸 후학습자 장학생으로 선발되지 않음\nㅇ 의무사항\n-\n수혜학기 이수 필수(휴학, 자퇴 등 학적변동 시 장학금\n전액\n반환)\n- 수혜학기 심사기준일(1학기 1.1., 2학기 7.1.)로부터 1년 이내 수혜학기 당\n4개월 의무재직 이행\n필요. 의무재직 인정 기업 등 상세 내용은 업무처리기준 참고\n※ 의무사항 불이행 시, 장학생 자격 상실되며 4개월 중 미이행한 날짜를 계산하여 지원 금액 반환\nㅁ 제출서류\nㅇ 장학금 신청 시\n- (고등학교 졸업 유형) 직업계고 고등학교 졸업증명서(학과명 표시 필수), 일반계고 위탁과정 수료증\n- (전문학사 예외 선발 기준 해당자) 전문학사 취득자가 전공심화과정 및 4년제 대학에 신편입하는 경우, ‘전문학사 취득 전’ 산업체 재직기간 2년(군복무기간 미포함)을 별도로 충족하면 장학금 지원 가능\n-> 대학졸업증명서(학위취득일 전 재직기간 2년 충족 여부 확인용 필수제출)\n※ 전문학사 취득자는 선발배점의 출신고교 항목에서 기학사로 별도 배점, 고등학교 졸업 유형(직업계고 졸업 등)에 대한 서류 제출 불필요\n- 본인명의 가족관계증명서(부모기업 재직여부 확인위한 필수 서류)\n* 상기 서류는 10월 중 이의신청 기간에도 제출 가능\nㅇ 이의신청(심사요건 재확인) 시\n- 10월 중 본인의 심사내용을 확인하고, 심사내용이 실제와 다른 경우 증빙서류 제출 필요\n※ 재직여부 증빙 및 선발배점 반영을 위한 서류 제출 가능\n※ 이의신청 서류 제출기간 내 서류 제출 필요(기간 종료 후 서류 제출 불가, 심사 기간 중 심사 결과 수시 확인 필요)\n- 상세내용은 10월 중 이의신청 관련 공지사항 통해 반드시 확인\nㅁ 문의처 : 희망사다리 상담센터 1800-0499 ['이미지 없음']"
    },
    {
        "title": "2025-1학기 교내장학금 신청안내(다문화, 장애인자녀, 장애대학생, 특수환경지원 장학금)",
        "url": "https://www.jj.ac.kr/jj/community/notice/janghaknotice.jsp?mode=view&article_no=446248&amp;board_wrapper=%2Fjj%2Fcommunity%2Fnotice%2Fjanghaknotice.jsp&amp;pager.offset=40&amp;board_no=1077",
        "content": "2025-1\n학기 교내장학금을 지급하고자 하오니 신입생 및 재학생은 다음 내용 확인 후 장학금 신청 바랍니다.\n1. 신청장학금: 교내장학금(다문화, 장애인자녀, 장애대학생, 특수환경지원)\n2. 신청기한: 2025. 1. 27.(월) ~ 2025. 2. 11.(화) 16:00\n3. 접 수 처: 학생회관 226호(학생지원실) 또는 e-mail(breeze@jj.ac.kr)\n4. 제출서류\n장학명\n장학금액\n자격요건\n제출서류\n다문화\n장학금\n50만원\n가. 다문화 가정의 이주민(결혼이민자) 혹은 다문화 가정의 자녀\n나. 직전학기 취득학점 12학점 이상, 평점평균 2.0 이상\n가.가족관계증명서\n나.외국인등록증,혼인관계증명서 등\n※ 국적 확인이 가능한 서류제출\n장애인자녀\n장학금\n수업료 50%\n가. 부·모의 장애 정도가 \"정도가 심한 장애인”인 경우\n나. 직전학기 취득학점12학점 이상, 평점평균 2.5 이상\n가.장학금 신청서(붙임문서 참조)\n나.가족관계증명서\n다.장애인증명서(부 또는 모)\n장애대학생\n장학금\n- 장애정도가 심한\n장애인: 200만원\n- 장애정도가 심하지\n않은 장애인: 50만원\n가. 직전학기 취득학점 관계 없음, 평점평균 2.0 이상\n가.장학금 신청서(붙임문서 참조)\n나.장애인증명서(본인)\n특수환경지원\n장학금\n- 수업료 60% 및 학업장려금 50만원\n유형 1: 아동복지시설에서 재원한 사실이 있는 자\n유형 2: 부모가 모두 사망하였거나 가출•행방불명인 자\n유형 3: 한부모가정의 부 또는 모가 교도소 수감 중인 자\n직전학기 취득학점 12학점 이상, 평점평균 2.0 이상\n가. 주민등록등본\n나. 유형별 해당 증빙서류\n5. 기타 유의사항\n가.\n신규자에 한하여 신청\n(\n입학 후\n1\n회 신청하면 매 학기 지급\n)\n나. 최종 선정자는 수업료 범위 내에서 고지서 선 감면 지급하며, 국가장학금 등의 중복지급으로 인해 장학금액 전액을 수혜받지 못하는\n경우가 발생 할 수 있음\n다. 신청자 중 장학금 지급 부적격 사유가 있는 자는 지급 불가함\n※ 문의: 063-220-2167\n붙임  장애인자녀 및 장애대학생 장학금 신청서 1\n부 ['이미지 없음']"
    },
    {
        "title": "주거안정장학금 신청(2/4 화~3/18 화) 안내",
        "url": "https://www.jj.ac.kr/jj/community/notice/janghaknotice.jsp?mode=view&article_no=446194&amp;board_wrapper=%2Fjj%2Fcommunity%2Fnotice%2Fjanghaknotice.jsp&amp;pager.offset=40&amp;board_no=1077",
        "content": "2025학년도부터 신설된 국가장학금(주거안정장학금) 신청기간을 안내하오니,\n원거리\n대학에 다니는\n기초/차상위학생\n은 신청 바랍니다.\n(신청방법은 첨부된 파일 참고!!) [\" \\n\\n25. 2. 4. (화) 9시 ~ 3. 18. (화) 18시\\n\\n \\n   \\n   \\n\\n \\n\\nAVSHS\\n원거리 대학에 다니는 기초:차상위학생(단.사입잠여대학에 한함)\\n\\n대학소재지 기준 부모님의 주소지가\\n\\n다른 교통권에 있는 경우\\n\\n#대도시권역 : 수도권 / 부산 ㆍ울산권 / 대구권 / 광주권 / 대젼권\\n{지역 : 인접(시외 경계를 맞당고 있는:시까지\\n\\nCBN Hest BAS ATA\\n\\n※상세 범위는 한국장학재단 누리집 참고\\n\\n \\n  \\n\\n솜 지원금액\\n\\n학기 중최대 월 20만원한도내\\n\\nAss\\n\\n학생이 제줄한주거안정장학금 지급 요청서 검토 후\\n\\n월 지급 한도 내에서 학생이 지출한 비용(실비)을 개별 지급\\n(학제별, 학생별 한도 내)\\n\\nft MEAS BGS! Siz\\n\\n'25. 2. 4.(화) 9시 ~ 3. 25. (Sh) 184]\\n\\n(2 서류제출 대상자는 온라인으로 서류제출 필수!\\n\\n6) 23부\\n\\n주거안점잠학금이란?\\n원거리 대학에 다니는\\n기초-차상위학생에게\\n\\n[주거관련 비용]을 지원하는 장학금\\n\\n※ 반드시 기간 내 신정\\n\\n   \\n  \\n\\nff Algor\\nLoon\\n\\nSta ashict Sele] Bt aupeletolal AV\\n*빈드시 학샘 본인이 시점 신정\\n\\n \\n\\n \\n\\n \\n\\n \\n\\n \\n\\n \\n\\n \\n\\n- 누리집                www, konaf.go.kr\\n한국장학재단   글           안정\\n콕잠학재단 장학금신정 } 신정서작성 + OES\\n+ SURRY\\nAndroid     106 '\\neae >) BB BISA > BENS\\n\\nff HAZ}\\n한국장화재탄\\n삼담센터\\n\\n1599-2000\\n\\x0c\"]"
    },
    {
        "title": "2025-1학기 국가장학금 2차 신청기간(2/4 화~3/18 화) 안내",
        "url": "https://www.jj.ac.kr/jj/community/notice/janghaknotice.jsp?mode=view&article_no=446176&amp;board_wrapper=%2Fjj%2Fcommunity%2Fnotice%2Fjanghaknotice.jsp&amp;pager.offset=40&amp;board_no=1077",
        "content": "2/4(화) 9시 ~ 3/18(화) 18시까지 국가장학금 2차 신청기간을 운영하오니,\n1차 신청 기간에 신청하지 못한 학생들은 필히 신청 바랍니다. [\"2025년 1학기[44\\n국가잠학금 신첨기간\\n'25.2.4.(화) 9시 a     |\\n\\n~3.18.(화) 18시   2 ;\\n\\n터,                     [\\n\\neer aaa |                                             :\\n\\nㅣ신청대상                             IMAM 및 가구원 동의기간\\n\\n신입고3, 재수생 통입화에절지) 편입생,  '25. 2. 4.(와) 9시 ~ '25. 5. 25.[화)78시\\nTHEI, Weta 및 1차 신첨블 봉친 재학생 ㅣ ㅣ, 포교을 대삼자는 온라인으로 서류제드 일시\\n\\n< 0646 7자전청이뢰이며, 자하 20어 새 ?시신지으 세즈 0 선철 2-3일 무 서랭페뜨 대실 며부를 반드시 확인이세요.\\n\\n \\n\\n \\n\\n바번                     누리집 NAL AAW REIS\\nㅣ신첨방법                     SSH Node tates\\n2 전지서명수탄한가지준비\\n.020인6서 6 2롤인6서 @간민요                       *＊ 하자금지원구간은 하생과가구원(부도또는배우자)이\\n소득평가액, 재산의소독환산액,험제자애수에 따른\\n< 안국잠아재탄 누리집 및 모바일앰매서 신정             공지멕을 반염하여 산정합니다\\nvwvrshoant goske\\nIalgzel\\n만피장외재탄상담벤터       a\\n1599-2000       BEE\\n\\n                                                                                                                                                                                                      \\n\\n \\n\\x0c\"]"
    },
    {
        "title": "2025학년도 1학기 국가근로장학금 (2차) 신청 안내(2. 4. 9시 ~ 3. 18. 18시)",
        "url": "https://www.jj.ac.kr/jj/community/notice/janghaknotice.jsp?mode=view&article_no=445954&amp;board_wrapper=%2Fjj%2Fcommunity%2Fnotice%2Fjanghaknotice.jsp&amp;pager.offset=40&amp;board_no=1077",
        "content": "<2025학년도 1학기 국가근로장학금 (2차) 신청 안내>\n2025학년도 1학기 국가근로장학금(2차) 학생 신청기간 및 신청 방법을 안내해드립니다.\nㅇ 국가근로장학금이란?: 지정된 근로지에서 근로하고 그에 따른 장학금을 월별 수혜\nㅇ 신청 대상:\n- 하계방학집중근로(2025년 7월~8월) 활동 희망자로,\n※ 금번 국가근로 2차 신청자는\n학기중 국가근로(2025년 3월~) 참여는 불가\n합니다.\n※\n국가근로 1차 신청자 중 하계방학집중근로에 참여를 희망하는 학생은 추후 희망근로지 신청만 진행하시면 됩니다(4~5월 중).\n금번에 국가근로 2차 신청을 다시 할 필요가 없습니다.\n- 우리 대학 정규학기 재학생 중 직전학기(2024-2) 백분위 성적이 70점 이상이며,\n- 당해학기(2025-1) 학자금지원구간(소득분위) 9분위 이하인 학생\n※ 근로장학사업 간의(국가근로 학기중, 보람근로, 대학생 청소년교육지원사업 등) 중복 참여 불가\nㅇ 신청 기간: 2025. 2. 4.(화) 09:00 ~ 3. 18.(화) 18:00\n(서류제출 및 가구원동의 기간: 2025. 2. 4.(화) 09:00 ~ 3. 25.(목) 18시\nㅇ 신청 방법:\n한국장학재단 홈페이지 또는 모바일 앱(상단 붙임문서 참고)\nㅇ근로 내용:\n- 하계방학집중근로 기간: 2025년 7월~8월 중\n- 근로지: 전국 교외 기관으로 주로 (준)공공기관(★ 교내 근로지는 미운영)\n- 시급: 12,430원(최대 근로시간은 300시간 내외로 변동 가능하며, 정확한 근로 기간 및 최대 근로 가능 시간은 추후 안내)\n- 하계방학집중근로 희망근로지 신청 필수(희망근로지 신청을 해야 신청이 최종적으로 완료됨): 2025년 4월~5월 중\n* 희망근로지 신청 기간은 한국장학재단에서 지정하며, 추후 학교 홈페이지 공지 예정\nㅇ문의\n- 한국장학재단 홈페이지, 모바일 어플 시스템 오류 등 문의 사항 1599-2290\n- 학생지원실 063-220-2162, 2172 ['이미지 없음']"
    },
    {
        "title": "중소기업 취업연계 장학사업(희망사다리1유형) 의무종사 기업기준 안내",
        "url": "https://www.jj.ac.kr/jj/community/notice/janghaknotice.jsp?mode=view&article_no=442807&amp;board_wrapper=%2Fjj%2Fcommunity%2Fnotice%2Fjanghaknotice.jsp&amp;pager.offset=40&amp;board_no=1077",
        "content": "중소기업 취업연계 장학사업 장학생은 아래 내용 필참하시기 바랍니다. ['Sidiwre                             한국장학재단                                oh\\n\\n \\n\\n \\n\\n;                   t         2\\n안내드리오니, 장학생 SA(Soil) 후 의무종사 미행 안내에 적극적인 활용을 요청 드\\n립니다\\nO ISSA SA SAIS WE\\n\\n \\n\\n구분                       인정불가 기준\\n\\n \\n\\n대기업, 중견기 멈(매출액 5.000먹원 초과), 비영리법인,\\nABER         국가-지방자치단체, 공기업-공공기관 및 자회사, 비사업자-종교단체\\n외국법인, 부모기업(부 또는 모가 대표자)\\n\\n \\n\\n \\n\\n계약방식       프리랜서, 특수형태 근로종사자(예 : 보험설계사, 택배원 등)\\n\\n \\n\\n취업지원형 | 청소년유해업소, 주점업, 사행시설 등\\n\\n \\n\\n창럽지원혈\\n\\n \\n\\n \\n\\n소속학과에 따른 진로 안내 필요\\n[유마교육] 어린미집-유치원 중 비멸리기관민\\nZI\\n\\nJ 82a 중 비명리기\\n\\n  \\n\\n기타\\n\\n \\n\\n \\n\\n \\n\\n \\n\\n \\n\\n니 의무종사 보고 방법\\n\\x0c', '빙자료를 재단 홈페이지로 보고\\n\\n \\n\\n춰 창업 기간 확인\\n\\n \\n\\n건강보험자격득실확인서\\n(또는 4대보험 가입기간 증빙서류)\\n\\n \\n\\n \\n\\n \\n\\n|업확인서)       부가가치세과세\\n\\n \\n\\n \\n\\n \\n\\n준증명원 등\\n\\n \\n\\nㅣ 기준의 주요내몽이며, 학기-사례에 따른 변동\\n\\n업무처리기준 확인이 필요함\\n\\x0c']"
    },
    {
        "title": "국가보훈장학금 국고보조금 신청 안내",
        "url": "https://www.jj.ac.kr/jj/community/notice/janghaknotice.jsp?mode=view&article_no=355705&amp;board_wrapper=%2Fjj%2Fcommunity%2Fnotice%2Fjanghaknotice.jsp&amp;pager.offset=40&amp;board_no=1077",
        "content": "국가보훈대상자 국고보조금 신청 안내\n국가유공자 등 예우 및 지원에 관한 법률에 따라, 국가유공자 본인 또는 가족에게 장학금을 지급하고 있습니다.\n대상자는 보훈처에서 해당 서류를 발급받아 학생지원실로 제출해주시기 바랍니다.\n◎ 대상자 여부 확인 및 서류 발급: 해당 지역 보훈처에 문의\n◎ 서류 안내\n구분\n제출 서류\n비고\n국가유공자 본인  또는 배우자\n교육지원대상자증명서\n3개월 이내 발급분\n국가유공자의 (손)자녀\n대학수업료등면제대상자증명서\n〃\n◎ 장학금액\n- 본인: 수업료 전액(초과학기 포함)\n- (손)자녀: 수업료 전액(정규학기 8회) - 단, 직전학기 성적 70점이상 유지하여야 계속 수혜 가능\n◎ 제출기간: 최소 당해학기 시작 1개월 전에 제출하여야 당해학기부터 적용 가능(1학기는 1월 말, 2학기는 7월 말)\n- 금번 2023-2학기는 2023. 8. 3.(목) 16시까지 제출하여야 적용가능\n- 이미 수혜받고 있는 학생은 제출하지 않아도 됨\n◎ 참고사항: 최초 1회 제출(면제여부 검토 후 계속 지급)\n◎ 제출처 및 문의: 전북 전주시 완산구 천잠로 303 학생회관 226호 학생지원실 (063-220-2982) ['이미지 없음']"
    },
    {
        "title": "★교내외 장학금 수령 계좌 inSTAR 등록 방법 안내★",
        "url": "https://www.jj.ac.kr/jj/community/notice/janghaknotice.jsp?mode=view&article_no=351217&amp;board_wrapper=%2Fjj%2Fcommunity%2Fnotice%2Fjanghaknotice.jsp&amp;pager.offset=40&amp;board_no=1077",
        "content": "교내외 장학금 수혜용 계좌 inSTAR 등록 방법 안내\n♣ 입력기간 : 상시\n♣ 입력방법\n- inSTAR → 장학/등록 → 장학관리 → 장학금 지급계좌관리\n- 지급계좌 변경 시, 재입력 후 저장시 등록완료\n♣유의사항\n- 본인 계좌 가능(부모, 형제, 친구, 지인 계좌  불가)\n- 입출금 통장 가능(청약, 적금통장, 휴면계좌 등 불가) ['Mle See\\n(1) 장학/등록 > 2) 장학 관리 (장학금 지급계좌관리) ~> 6 학생 본인 통장계좌 입격 0000엔\\n\\n간편등록!\\n\\n \\n\\notto\\n\\nCEs (eit)\\n\\n \\n\\n \\n\\n  \\n     \\n   \\n\\nith\\n\\nClee rr)        LS\\n\\nUsername\\n\\nD LyQ] Alea\\nPassword\\n\\n\" 대확에서는 국가장학금을                 장학금,             현금 지급하는 모든 형태의 장학금을 상기에 입력한 계좌를 동해 ?               ca\\n국가장학금을 포함하여 한국장학            도 가능한 이 계죄와 동일하게 관리하여 주시기 바랍니다:                                 ㅣ\\n\\nae. 기타 타인의 계좌가 0                 의 계좌이어야 하며,\\n유로 계좌를 변경해야 할 경                   } 계좌는 재학기간\\n\\n무지급계좌이력\\n\\x0c']"
    },
    {
        "title": "2024년 2학기 중소기업 취업연계 장학금(희망사다리Ⅰ유형) 신규장학생 신청 안내(9. 2. 9시~9. 13. 16시)",
        "url": "https://www.jj.ac.kr/jj/community/notice/janghaknotice.jsp?mode=view&article_no=439360&amp;board_wrapper=%2Fjj%2Fcommunity%2Fnotice%2Fjanghaknotice.jsp&amp;pager.offset=40&amp;board_no=1077",
        "content": "< 중소기업 취업연계 장학금(희망사다리Ⅰ유형) 신규장학생 선발 >\n중소기업 취·창업 및 청년 지원 확대를 위하여\n학자금지원구간과 무관하게\n,\n중소·중견기업 취업 또는 창업을 희망하는 재학생 대상으로 (중소·중견기업에 기취업한 재학생, 기창업한 재학생 모두 신청 가능)\n등록금 전액\n과 매학기\n취·창업지원금 200만원\n을 지원합니다.\n안녕하세요, 한국장학재단입니다.\n2024년 2학기 중소기업 취업연계 장학금(희망사다리Ⅰ유형) 신규장학생 선발을 위한 학생신청 기간을 공지하오니, 중소·중견기업 취업 또는 창업을 희망하는 학생들의 많은 관심과 신청 바랍니다.\n□\n참여대학 신청 기간\n:\n2024. 8. 28.(수), 09:00 ~ 9. 6.(금) 16:00까지 (※신청기간 엄수)\n□\n학생신청 기간\n:\n2024. 9. 2.(월), 09:00 ~ 9. 13.(금) 16:00까지\n(※신청기간 엄수)\n※ 본 사업은 신청서 작성 후 온라인사전교육(진단평가)까지 모두 이수해야 최종신청이 완료됩니다.\n마감일 최소 하루 전부터 시간을 넉넉히 잡으시어 장학금을 신청하는데 차질이 없으시기 바라며\n, 본인의 장학금 신청완료 여부, 온라인사전교육(진단평가) 이수여부를 꼼꼼히 확인 바랍니다.\n(신청매뉴얼 필독)\n□  지원대상\nㅇ (기본요건)\n대한민국 국적자로 일반대 3학년 이상 또는 전문대 2학년 이상의 학생이며, 대학의 최소이수학점 이상을 이수하고\n(대학의 최소이수학점 기준이 없는 경우 12학점 이상 이수),\n직전학기 성적이 100점 만점의 70점 이상인 자\n※ 연도·학기별 사업 참여대학의\n재학생이어야 함\n(참여대학 유무는 소속 대학으로 문의 시 확인 가능)\n- 취업지원형: 기본요건을 충족하는 학생 중 중소·중견기업 취업(희망)자\n- 창업지원형: 기본요건을 충족하는 학생 중 창업(희망)자\n※\n취업 여부는 장학금 신청과 무관\n(기취(창)업자, 취(창)업 희망/예정자 모두 지원가능)\n※  본 장학금 기존 수혜자 중 전문대 장학생이 졸업 후 전공심화 또는 4년제 편입하는 경우, 전공심화/편입한 첫 학기에 한해 신규로 재신청 가능\n※  조기취업형 계약학과는 1학년에 한해 신청 및 지원 가능\n※ (일자리사업 중복참여 금지) 직접일자리 사업은 중소기업 취업연계 장학사업 참여기간 내 중복참여가 불가하며, 기타 참여가능 사업은 고용노동부로 문의\n□  지원내용\nㅇ\n(\n등록금\n)\n수혜학기 등록금 전액\n- 수혜학기 중복지원 여부와 등록금액에 따라 장학금액 변동가능\n- 장학생 지원기준을 충족하지 못할 시 장학금 지원 중단\nㅇ\n(\n취\n·\n창업지원금\n)\n수혜학기 당\n200\n만원\n- 매 학기 직무기초교육 이수자에 한해 지원\n□  신청방법: 재단 홈페이지 신청서 작성 (온라인사전교육(진단평가) 이수 필수)\n※ 신청기간 내 반드시 온라인사전교육(진단평가)를 이수 완료하여야 장학신청이 완료됩니다.\n□  필수 제출서류: 취·창업지원금 사용계획서 (미제출 시 해당 평가 항목 0점 처리)\n※ 붙임파일 또는 신청서 작성 시 제출화면에서 양식 다운\n□  장학생 의무사항\nㅇ\n(보증보험)\n매 학기 보증보험 개인정보 제공동의 필수\n(보증보험 동의시작일 기준 미성년자는 제외, 보험료는 재단에서 부담)\n※ 보증보험 개인정보제공 동의 일정은 별도 공지예정(홈페이지 > 공지사항 게시 및 LMS 안내* 예정)\n* 문자 및 알림톡 수신을 위한 재단 홈페이지 내 본인 연락처 최신화 필수(변경 후 연락처 미수정으로 인한 안내 누락될 경우 장학생 최종선발에서 탈락될 수 있으며, 구제 불가함에 유의)\nㅇ (자격유지)\n- 수혜학기 학적 상태(재학) 유지 (※ 휴학, 졸업(유예) 등 재학이 아닌 학적 학기에 지원 불가)\n- 대학의 최소이수학점 이상(대학 최소이수학점 기준이 없는 경우 12학점 이상 이수)을 이수하고, 직전학기 성적이 백분위 70점(C0) 이상\nㅇ (의무교육) 매 학기 직무기초교육 이수 필수 (미이수 시 해당학기 취·창업 지원금 반환)\nㅇ (의무종사) 졸업 후 ‘수혜학기(횟수) x6개월’간 중소·중견기업에 취업 또는 장학생 선발 이후 창업 상태 유지하여 의무재직 이행\n※ 의무종사 인정 기준 등은 업무처리기준에 상세히 설명되어 있으므로, 필히 확인 후 신청(재단 홈페이지 → 고객센터 → 자료실)\nㅇ (장학금 반환)\n- 매 학기 재단이 정하는 직무기초교육 미이수 시 장학금 반환\n- 휴학, 자퇴 등 학적변동 발생 시 장학금 반환\n※ 단, 휴학은 종류와 관계없이 최대 3년까지 인정, 3년 초과 시 자격 상실\n※ 자퇴 및 제적의 경우 의무종사 불가에 따라 기수혜장학금 전액 반환 필수\n감사합니다.\n☎\n문의\n: 1800-0499(\n취업연계 상담센터\n)\n- 통화대기량이 많습니다. 본 게시글 및 붙임파일의 신청매뉴얼을 먼저 참고해주시기 바랍니다. ['이미지 없음']"
    },
    {
        "title": "2024-2학기 국가근로장학금 신규장학생 운영 안내",
        "url": "https://www.jj.ac.kr/jj/community/notice/janghaknotice.jsp?mode=view&article_no=439207&amp;board_wrapper=%2Fjj%2Fcommunity%2Fnotice%2Fjanghaknotice.jsp&amp;pager.offset=40&amp;board_no=1077",
        "content": "<2024-2학기 국가근로장학금 신규장학생 운영 안내>\n국가근로장학사업 주요 운영 사항 및 근로 시작 전 필수 실시 사항을 안내하오니 반드시 숙지하시고 진행해주시기 바랍니다.\n1. 근로 시작 전 필수 실시 사항(아래 그림과 첨부파일 참고)\n가. 서약서 작성 및 사이버 O.T. 수강(장학재단 홈페이지)\n-첨부파일 13~15P참고\n나. 학업시간표 등록★\n-첨부파일16~18P참고\n-장학재단 지침상, 수업시간에는 근무할 수 없음. 학업시간표를 등록해두고 그 시간 외에 출근부를 입력하는 것이 학업시간표 등록의 목적임\n-등록 기한: 9. 11.(수) 자정까지(수강취소 반영까지 완료해야 함)\n-진로설계세미나(진로탐색)과목\n등도 시간표에 반드시 등록\n-★학사시스템에 등록된 그대로 정확한 수업시간표 입력\n(입력된 수업시간표가 실제와 달라 부정근로 등의 문제 발생 시, 장학생 본인에게 책임이 있고 장학금 환수, 근로 참여 제재를 받게 됨)\n-일시적인 휴강\n이 발생하여도\n그 시간에는 근로 불가\n하고 인정되지 않음\n-온라인 수업이어도 학사 시스템상 수업 시간이 정해져\n있는 경우, 반드시 입력해야 함\n다. 업무스케쥴 입력\n-첨부파일 19~21P참고\n-입력 기한: 9. 1.(일)\n~\n근로 시작 전날까지\n-어떤 요일에 몇 시부터 몇 시까지 몇 시간 동안 근무할지 근로 시간표를 정하는 것\n-근로지 담당 선생님과 상의하여 업무스케쥴 작성\n-근로지에서 근로 시작일 전에 학생에게 연락할 예정\n-아래\n‘최대 근로 가능 시간’을 참고하여 범위 내에서 업무스케쥴을 작성\n일/주/월별 최대 근로 가능 시간\n<학기중(9월~11월)>\n1일 최대 8시간\n1주 최대 15시간\n1개월 최대 60시간\n-작성한 업무스케쥴을 출근부 어플에 입력해야 하며, 업무스케쥴을 입력하여야 출근부가 활성화 됨\n2. 근로 시작 후 필수 실시 사항\n(아래 그림과 첨부 파일 참고)\n가. 사전교육 이수보고서 작성 및 제출\n(근로지 담당자에게 교육을 받은 후 보고서를 작성하고 담당자 서명을 반드시 기입하여 장학재단 홈페이지에 탑재, 방법 첨부파일 22~24P 참고)\n-양식: 첨부파일 참고\n나. 근로지 상호평가\n(근로지 담당자와 학생이 상호 평가, 첨부파일 32P 참고)\n- 근로 시간 40시간 초과 시 1차 평가 필수, 160시간 초과 시 2차 평가 필수\n※가, 나. 미이행 시 출근부 제출이 안됨\n3. 출근부 입력 및 제출 관련 사항\n가. 출근부 입력 방법(붙임 첨부파일 25~28P 참고)\n나. 출근부는 출퇴근 즉시 입력이 원칙\n다. 불가피하게(출근부 앱 오류) 출근부 입력이 안된 경우, 근로지 담당자에게 수정 요청\n(단, 수정 횟수의 제한이 있으며, 수정이 계속될 경우 향후 한국장학재단의 부정근로 모니터링 대상이 될 수 있음)\n라. 점심시간은 근로 시간에서 제외\n마. 근로지에서 출근부 대학제출이 익월 초일까지 이뤄질 수 있도록 협조(1개 근로지라도 제출이 늦어질 경우 장학금 지급 지연될 수 있음)\n4. 자체 사전교육(오리엔테이션) 참여 안내\n아래 일정 중 1회 필수 참석, 미참석 시 근로 불가, 약 1시간 진행\n- 9/2(월) 저녁 6시 10분,\n학생회관 3층 수퍼스타홀\n(기존 온누리홀에서 변경됨)\n- 9/3(화) 저녁 6시 10분, 학생회관 3층 수퍼스타홀\n5. 2024-2학기 주요 운영 사항\n가. 근로 기간: 2024. 9. 2.(월)~2025. 2. 28.(금)\n나. 시급: 교내 9,860원 / 교외 12,220원\n다. 장학금 지급일: 익월 15일 경(9월 근무분은 10월 15일 경에 국가근로 신청 시 장학재단에 입력한 계좌로 입금, 출근부 제출 지연 시 지급이 지연될 수 있음)\n라. 일/주/월별 최대 근로 가능 시간\n<학기중(9월~11월)>\n1일 최대 8시간\n1주 최대 15시간\n1개월 최대 60시간\n<방학중(12월~2월)>\n미정, 추후 안내\n마.\n국가근로 장학생 준수 사항 및 근로자격 해제 사유\n국가근로 장학생의 경우 ‘다음’ 내용을 준수하여 근무하여야 한다.\n다음 내용 중 ‘1-6번’을 준수하지 않아 근로지 담당자로부터 2회 이상 경고를 받고 개선하지 않을 경우, 또는 ‘7-8번’에 해당할 경우,\n근로지 담당자는 학생지원실로 해당 학생의 “근로 중지”를 요청 할 수 있다.\n학생지원실은 “근로 중지”를 요청 받은 다음날부터\n해당 학생의 “근로 자격을 해제” 한다\n.\n근로 자격을 해제 받은 시점부터 해당학기 근로(국가근로, 대학생 청소년교육지원사업, 보람근로)장학에 참여할 수 없다.\n-다음 -\n1. 출.퇴근 시간을 준수하며, 무단결근과 근로지 무단이탈을 하지 않는다.\n2. 근무시간을(스케쥴) 수시로 변경하지 않는다.\n3. 근무지의 업무 요청에 불응하거나 직무태만하지 않는다.\n4. 불손한 태도로 근무지 분위기에 부정적인 영향을 주지 않는다.\n5. 부정근로를 하지 않는다.(근로시간 허위 입력 등)\n6. 기타 근로장학생으로서 근로 태도가 불량하거나 의무를 다하지 않는 일이 없도록 한다.\n7. 배정된 근무지에서 근로학생이 업무수행이 불가능하다고 할 경우 ‘근로 중지’ 된다.\n8. 학사징계 혹은 법적 처벌을 받은 경우 ‘근로 중지’ 된다.\n6. 기타 중요 사항\n가. 근로장학은 학적이 ‘재학’인 경우만 실시 가능함.\n학적변동 시 근무 불가\n(휴학/자퇴 ‘신청일’ 전날까지만 근무 가능하며, 제적/졸업 ‘발생일’ 전날까지만 근무 가능함)\n나. 타 장학사업과 중복 근로할 수 없음\n(보람근로, 대학생 청소년교육지원사업, 학기중에 국가근로에 참여한 경우 방학집중근로에 지원 불가)\n다. 부정근로(허위근로, 근무시간 오입력, 대체근로-실제 근무 시간과 출근부에 입력한 시간이 다른 경우, 대리근로 등) 적발 시 졸업 시까지 사업 참여 불가\n및 장학금 반환\n라. 출근부 제출은 익월 첫째날까지 완료되어야 함\n마. 근로지 담당자 또는 직원과 가족관계, 친인척 관계, 기타 이해관계가 있는 경우 근로 불가\n하며, 해당 시 학생지원실 담당자에게 통보해야 함\n바. 문의 전화: 출근부 어플 및 홈페이지 오류 등: 한국장학재단 콜센터 1599-2290 ['이수보고서\\n작성 및 제출\\n\\n \\n\\n<국가근로 진행 순서>\\n! _서약서및 |\\n\\n는 사이버07\\nLouw?\\n\\n‘ “\\n0\\n[대        z\\n\\nRW    q %          gy\\n\\n=,           101                 xo M1\\n110                        K\\nKd        +.             a\\n\\x0c']"
    },
    {
        "title": "2024년도 인천 청년 해외 배낭연수 장학생 선발 공고(~9. 18. 23시)",
        "url": "https://www.jj.ac.kr/jj/community/notice/janghaknotice.jsp?mode=view&article_no=439148&amp;board_wrapper=%2Fjj%2Fcommunity%2Fnotice%2Fjanghaknotice.jsp&amp;pager.offset=40&amp;board_no=1077",
        "content": "자세한 사항 붙임 파일 참고 ['이미지 없음']"
    },
    {
        "title": "(신청기간 정정)2024-2학기 대학생 청소년교육지원사업 신규장학생 추가모집 (9. 1.~9. 6.)",
        "url": "https://www.jj.ac.kr/jj/community/notice/janghaknotice.jsp?mode=view&article_no=438920&amp;board_wrapper=%2Fjj%2Fcommunity%2Fnotice%2Fjanghaknotice.jsp&amp;pager.offset=40&amp;board_no=1077",
        "content": "(신청기간 정정)\n기존: 8. 26.(월)~9. 6.(금)\n정정: 9. 1.(일)~9. 6.(금)\n※ 한국장학재단 시스템상 2학기 신청기간 기본값이 9월 1일부터로 대학에서 임의 변경 할 수 없어\n신청기간을 정정하오니 양해부탁드립니다. 감사합니다.\n-------------------------------------------------------------------------------------------------------------------------------\n2024-2학기 대학생 청소년교육지원사업 신규장학생 추가모집\n(9. 1.~9. 6.)\n대학생 청소년교육지원사업이란, 대학생이 초‧중‧고교 학생을 대상으로 고등교육과정을 통해 얻은 지식과 경험을 나누고, 장학재단은 대학생에게 미래 인재로 성장할 수 있는 기회와 장학금을 제공하는 장학사업입니다. 2024학년도 본 사업에 참여할 대학생 멘토를 아래와 같이 모집합니다.\n가. 모집 유형: B형(멘토 발굴형) / 신청하는 학생이 직접 활동할 기관을 발굴하여 활동\n나. 활동 가능 기관: 지역아동센터, 학교 밖 청소년지원센터, VMS/1365(정부인증포털)등록시설, 청소년방과후아카데미 운영시설(한국청소년활동진흥원 인증)\n다. 활동 기간: 2024. 9. 사전교육 이후 ~ 2025. 2.\n※ 예산 가용 상황에 따라 2025. 1월에 조기 종료 될 수도 있음\n라. 신청 자격: 학과 제한 없음, 직전학기 성적이 백분위 70점 이상인 정규학기 8학기 이하 재학생\n※ 조기취업자, 초과학기생, 휴학/제적/자퇴자 지원 불가\n※ 직전학기 성적이 없는 2024-2학기 편입생 지원 불가\n마. 신청 기간:\n2024. 9. 1.(일)~\n9. 6.(금)\n바. 신청 방법: 한국장학재단 홈페이지(www.kosaf.go.kr)-인재육성-대학생 청소년교육지원사업-사업신청-신청서 작성-완료\n※ 신청서에 첨부해야하는 제출서류 별도로 없음\n※ 2024-1학기 모집 시 신청했던 학생의 경우,\n대청교가 연간 사업이기 때문에 시스템상 재신청이 불가한 상태임. 별도로 한국장학재단에 공문을 발송하여야 2학기 신청이 가능하게 시스템이 바뀌므로, 해당되는 학생은 다음 구글 폼에 인적사항 기재(9월 6일까지)\nhttps://forms.gle/H2e1otxw1RejpHzW6\n→ 시스템 문제가 해소되면 학생들에게 별도로 문자 공지(9월 12일 목요일 예정) → 2학기 대청교 참여 신청(해당 학생들만 신청기간 9월 12일~9월 15일까지 연장)\n사. 선발 인원: 12명\n아. 선발 기준\nㅇ 직전학기 성적 우수자를 우선 선발\nㅇ 직전학기 성적이 동점일 경우, 직전학기 이수학점이 높은 학생을 우선 선발\nㅇ 직전학기 성적 및 이수학점이 동일할 경우, 이수학기가 높은 학생을 선발\n자. 선발자 발표: 2024. 9. 19.(목) 예정 (변동 가능)\n차. 자체사전교육(오리엔테이션) 안내(변동 가능)\nㅇ선발된 학생만 해당\nㅇ일시: 9. 23.(월) 18시 10분(1시간 소요)\nㅇ장소: 학생회관 3층 한국어교육센터 내 강의실\nㅇ활동을 위한 필수 사항으로 미참여 시 선발 취소\n카. 시급 및 최대 근로 가능 시간: 12,220원, 학기 최대 400시간\n타. 선발 및 활동 개시 전까지 과정(사전교육 때 자세히 설명 예정): 학생 신청→ 심사 및 선발→ 사전교육 실시→선발된 학생이 기관 섭외(멘토발굴형)→ 학생이 섭외한 기관과 협의하여 활동계획서 작성 및 학생지원실에 제출(9. 24.~10. 1.까지)→담당자가 기관과 학생 시스템상 매칭→활동 시작(기관-학생 시스템상 매칭 완료 후부터)\n파. 유의사항\n- 국가근로, 보람근로 등 타 근로 장학사업과 중복 참여 불가\n- 학적정보(신청정보)가 정확하지 않을 경우, 선발이 불가\n하. 어플 및 홈페이지 시스템 오류 관련: 한국장학재단 1599-2000 ['이미지 없음']"
    },
    {
        "title": "(수정공고) 2024년도 (재)광산장학회 장학생 선발 공고(~9. 6.)",
        "url": "https://www.jj.ac.kr/jj/community/notice/janghaknotice.jsp?mode=view&article_no=438768&amp;board_wrapper=%2Fjj%2Fcommunity%2Fnotice%2Fjanghaknotice.jsp&amp;pager.offset=40&amp;board_no=1077",
        "content": "자세한 사항 붙임 파일 참고 ['(자)광산장학회 공고 제2024-2호\\n\\n2024년도 (재)광산장학회\\n\\n \\n\\n \\n\\n \\n\\n \\n\\n \\n\\n \\n\\n \\n\\nJa            지속적인 학업을                   록 지원\\n「2024년도 (재)광산장학회 장학생」 선발계획을 아래와 같이 공고합니다.\\n2024년 8월\\n재단법인 광산장학회 이사장\\n|. 선발개요\\n가. 선발인원: 165명(예정)                              안위 : 명)\\n구 분       제    Sas] BD     Hee CH    종합대\\nAl         165       10        5       40      110\\n우수장학생       50        -        -       15       35\\n일반장학생       80        -        >       15       65\\n득기장학생        5        -        5        -        -\\n득정장학생       20                -       10       10\\n학교밖청소년장학생      10       10        -        :        -\\n\\n \\n\\n \\n\\n \\n\\n \\n\\n \\n\\n \\n\\n나, 장 학 금: 중:고생*학교밖청소년 50만원, 전문대 150만원, 종함대 200만원\\n다. 선발절차\\n\\n0 선발공고 및 신청접수          : 8. 19. ~ 9. 6. 05일간)\\n6 장학생 선발 심사               9. 7. ~ 10. 18. (259%)\\n6 심사위원희 개최              : 10. 25. (예정)\\n0 이사회 의결                 : 11. 1. (예정)\\n0 최종 선정 발표               : 11. 6. (예정)\\n0 장학금 지급                 : 11. 11. (예정)\\n0 장학생 장학금 수여식           : 11. 21. (예정)\\n\\n＊ 선발인원 및 추진일정은 사정에 따라 조정될 수 있으며, 최종 선발자 발표는 광산구청 홈페이지 게재(개별동보)\\n\\x0c', \">\\n\\n11. 장학금 신청\\n가. 신청접수\\n0 기간: '24. 8. 19. ~ 9. 6.05일간)\\n0 신청방법: 방문 혹은 우편접수 (9일 <일사지 우체국 소인에 한함)\\n※ 제출서류는 원분이어야 하며, 미제출시 서류미비로 보완전차 없어 닫락\\n0 신 청 A: BAER SH] 0] 2] (www.gwangsan.go.kr)\\n광산구소개 - 광산장학회 - 장학회소식 - 공지사항\\n접 수 처: (재)광산장학희 사무국 (숄960-7926)\\n(광주광역시 광산구 광산로 29번길 15 광산구청 6증)\\n\\n나. 신청자격\\n0 지원자격: 공고일 기준 광산구에 주민등록을 두고 1년 이상 거주하고\\n있는 주민과 그 자녀로 재학 중인 학생 또는 학교밖청소년\\n다. 신청요건\\n【우수장학생】\\n\\n- 2024년도 1학기 혹은 직전 학기 성적 3.5점5점 반점이상 및 대학\\n수학능력평가 전 과목 평균 2등급 이내\\n\\n* 타 장학금 중복 시 수령액을 제외한 차에 지급\\n\\n【일반장학생】\\n\\n- 2024년도 1학기 혹은 직전 학기 성적 3.0점(45점 반점이상 및 대학\\n수학능력평가 전 과목 평균 3등급 이내\\n\\n- 신청자 직계가족 국민건강보험료가 2024년도 기준 전국가구 중위소득\\n100%이내인 가구 (납입기간 : 24년 1월 ~ 7, OB)\\n\\n* 생활비 지원 장학금으로 타 장학금 중복여부와 상관없이 신청가능\\n\\n【득기장학생】\\n공고일로부터 1년 이내(23.8.19.~24.8.19.) 전국 및 국제대희에서 3\\n위 이내의 성적을 득한 학생\\n\\n- 단, 국가 및 지방자치단체에서 주최 또는 후원한 대희의 개인\\n부문에 한함\\n\\n- 신청자 직계가족 국민건강보험료가 2024년도 기준 전국가구 중위소득\\n100%이내인 가구 (납입기간 : 24년 1 ~ 7, OB)\\n\\n* 생활비 지원 장학금으로 타 장학금 중복여부와 상관없이 신청가능\\n\\x0c\"]"
    },
    {
        "title": "2024-2학기 국가근로장학금 희망근로지 신청 안내",
        "url": "https://www.jj.ac.kr/jj/community/notice/janghaknotice.jsp?mode=view&article_no=438625&amp;board_wrapper=%2Fjj%2Fcommunity%2Fnotice%2Fjanghaknotice.jsp&amp;pager.offset=40&amp;board_no=1077",
        "content": "<2024-2학기 국가근로장학금 희망근로지 신청 안내>\n국가근로장학금은 대학생에게 학자금(등록금 및 생활비)마련을 위한 근로 기회를 제공하고, 그에 따른 대가를 지급함으로써 안정적인 학업 여건을 조성하고, 사회 및 직업 체험을 통해 취업 역량을 제고하는 사업입니다. 2024학년도 2학기 학기중 근로를(2024년 9월~2025년 2월) 희망하는 학생은 희망근로지 신청이 필요하오니, 아래를 참고하시어 신청하시기 바랍니다.\n[※ 참고: 국가근로는 근로 기간에 따라 2가지 유형으로 나뉨]\n1. 학기중 근로: 근로 기간이 학기 전체(2024년 9월~2025년 2월), 국가근로 1차 신청자만 지원 가능, 근로지는 교내/외 근로지, 금번이 희망근로지 신청 기간\n2. 동계방학집중근로: 근로 기간이 방학에 한정(2025년 1월~2월), 국가근로 1/2/3차 신청자 모두 지원 가능, 근로지는 (준)공공기관 등 교외근로지로 한정, 희망근로지 신청기간이 금번이 아닌 별도로 운영됨(2024년 10월~11월 중, 추후 공지 참고)\n--------------------------------------------------------------------------------------------------------------------------------------------------------------\n1. 희망근로지 신청 가능 대상(★아래를 모두 충족한 학생)\n가. 2024-2학기 국가근로장학금 1차 신청 기간에 신청을 완료한 자(2차 신청자는 학기중 근로가 불가하고 동계방학집중근로 지원만 가능)\n나. 2024-2학기가 정규학기 8학기 이하(건축학과는 10학기 이하)\n★ 단, 편입생은 첫 학기에 한하여 학기중 근로를 지원할 수 없습니다. 동계방학집중근로에는 지원할 수 있으니, 동계방학집중근로 희망근로지 신청기간(10~11월 중 예정)에 희망근로지를 신청하시기 바랍니다.\n다. 학적이 ‘재학’ 상태(휴학, 자퇴, 제적, 졸업 등 불가)\n라. 직전학기 백분위 성적이 70점 이상\n마. 2024-2학기 학자금지원구간 9분위 이하(2024-1학기부터 9분위로 확대됨)\n바. 학기중 근로(2024. 9.~2025. 2.) 희망자\n※ 타 장학사업과 중복 참여 불가(국가근로 동계방학집중근로, 대학생 청소년교육지원사업 멘토링, 보람 장학 등)\n2. 희망근로지 신청 방법: 한국장학재단 홈페이지 또는 모바일 - [희망근로지신청 및 조회] / 첨부파일 매뉴얼 참고\n3. 신청 기간: 2024. 8. 15.(목) ~ 8. 19.(월) 자정까지\n4. 국가근로 장학생 준수 사항 및 근로자격 해제 사유\n국가근로 장학생의 경우 ‘다음’ 내용을 준수하여 근무하여야 한다.\n다음 내용 중 ‘1-6번’을 준수하지 않아 근로지 담당자로부터 2회 이상 경고를 받고 개선하지 않을 경우, 또는 ‘7-8번’에 해당할 경우,\n근로지 담당자는 학생지원실로 해당 학생의 “근로 중지”를 요청 할 수 있다.\n학생지원실은 “근로 중지”를 요청 받은 다음날부터\n해당 학생의 “근로 자격을 해제” 한다\n.\n근로 자격을 해제 받은 시점부터 해당학기 근로(국가근로, 대학생 청소년교육지원사업, 보람근로)장학에 참여할 수 없다.\n-다음 -\n1. 출.퇴근 시간을 준수하며, 무단결근과 근로지 무단이탈을 하지 않는다.\n2. 근무시간을(스케쥴) 수시로 변경하지 않는다.\n3. 근무지의 업무 요청에 불응하거나 직무태만하지 않는다.\n4. 불손한 태도로 근무지 분위기에 부정적인 영향을 주지 않는다.\n5. 부정근로를 하지 않는다.(근로시간 허위 입력 등)\n6. 기타 근로장학생으로서 근로 태도가 불량하거나 의무를 다하지 않는 일이 없도록 한다.\n7. 배정된 근무지에서 근로학생이 업무수행이 불가능하다고 할 경우 ‘근로 중지’ 된다.\n8. 학사징계 혹은 법적 처벌을 받은 경우 ‘근로 중지’ 된다.\n5. 장학생 선발 기준, 근로지 선호학과 관련 사항\n가. 희망근로지 신청 학생들 중, 학자금지원구간과 직전학기 성적 환산점수(비율 50:50) 합계 고득점자 선발\n※ 단, 근로지 업무 특성상\n선호학과가 있는 경우, 해당 근로지를 희망근로지로 신청한 학생 중 선호학과 학생을 고득점 순으로 우선 선발\n예) 정보통신지원실 선호학과: 정보통신공학과(1순위), 컴퓨터공학과(2순위), 스마트미디어학과(3순위)\n→ 정보통신지원실을 희망근로지로 신청한 명단에서, 정보통신공학과 학생 중 고득점자가 다른 학과 학생보다 우선 선발됨, 만약 정보통신공학과 학생이 없을 시, 컴퓨터공학과 학생 중 고득점자가 다른 학과 학생보다 우선 선발됨.\n나. 선호학과 정보는 근로지 모집공고 상세보기 클릭\n→ 상세직무내용 및 비고란을 통해 확인 가능\n다. 위의 ‘4. 국가근로 장학생 준수 사항 및 근로자격 해제 사유’의 8번 항목에 의거하여,\n학생이 선발되어 배정된 근무지에서 판단하기에 학생이 업무수행이 불가능하다고 할 경우 '근로 중지 처리'될 수 있으며, 이 때 다른 근로지로 재배정하지 않습니다.\n따라서 희망근로지 신청에 앞서 근로지 업무 내용 등을 잘 살피시어 본인이 업무 가능한 근로지로 신청하시기 바랍니다.\n6. 선발 결과 발표 예정일: 2024. 8. 28.(수) 오후 5시 이후\n<확인 방법>\n가. 선발여부: 한국장학재단 홈페이지-장학금-국가근로장학금-선정결과에서 상태가 `근로진행 ` 이면 선발됨\n나. 근로지 확인: 장학금-국가근로장학금-근로장학관리-출근부관리 메뉴에서 검색조건을 2024년 2학기 9월로 두고 검색했을 때 조회되는 근로지\n7. 자체 사전교육(오리엔테이션) 참여 안내\n가. 아래 일시 중\n1회 필수 참석\n(약 1시간 소요)\n나. 일시 및 장소:\n- 9/2(월) 저녁 6시 10분, 스타센터 온누리홀\n- 9/3(화) 저녁 6시 10분, 학생회관 3층 수퍼스타홀\n※ 아직 합격자 발표 전인데, 참석 불가하다는 연락은 자제하시기 바랍니다.\n다. 일시 및 장소는 상황에 따라 변동될 수 있으며, 합격자에 한해 사전 안내 예정\n8. 근로기간: 2024. 9. 2.(월) ~ 2025. 2. 28.(금)\n※ 학사일정 및 근로지 상황에 따라 근로시작 및 종료일자가 조정될 수 있음\n9. 시급: 교내 9,860원 / 교외 12,220원\n10. 월별 최대 근로 가능 시간\n가. 9월~11월: 월 60시간\n나. 12월: 월 80시간\n다. 1월~2월: 월 90시간\n※ 예산 상황에 따라 월별 최대 근로 가능 시간이 조정될 수 있음\n11. 참고사항\n가. 근로기간 및 근로시간 등은 근로지에 따라 상이할 수 있음\n나. 선발 인원은 예산 및 근로지 상황에 따라 변동될 수 있음\n다. 타 장학사업 중복 참여 불가(국가근로 방학집중근로, 대학생 청소년교육지원사업 멘토링, 보람장학 등)\n[문의] 한국장학재단 홈페이지, 어플 시스템 문제 관련 : 1599-2290 [' \\n\\n[\\n\\n \\n\\nSuen\\n\\n2 gan\\n\\n \\n\\x0c']"
    },
    {
        "title": "2024-2학기 국가장학금 신청기간(2차, 8/14~9/11) 안내",
        "url": "https://www.jj.ac.kr/jj/community/notice/janghaknotice.jsp?mode=view&article_no=438368&amp;board_wrapper=%2Fjj%2Fcommunity%2Fnotice%2Fjanghaknotice.jsp&amp;pager.offset=40&amp;board_no=1077",
        "content": "8/14(수) 9시부터 9/11(수) 18시까지 국가장학금 2차 신청기간을\n운영하오니, 1차 신청기간에 신청하지 못한 학생들은 신청 바랍니다. ['개감준비는 국장 신첨으로! \\\\ //\\n\\na\\n\\nGSE\\n\\n \\n\\x0c']"
    },
    {
        "title": "2024년 손태희장학재단 장학생 선발 안내(~9. 1.)",
        "url": "https://www.jj.ac.kr/jj/community/notice/janghaknotice.jsp?mode=view&article_no=438248&amp;board_wrapper=%2Fjj%2Fcommunity%2Fnotice%2Fjanghaknotice.jsp&amp;pager.offset=40&amp;board_no=1077",
        "content": "자세한 사항 붙임 파일 참고\n*추천서는 본인 학과 교수님이 작성하셔야 함.\n학교장(총장) 직인은 본인 학과 행정 조교 선생님께 요청 ['재단법인 손태희장학재단 공고 제 2024- 01호\\n\\n \\n\\n\" 손래회장학재단은 으수 인재들이 꼽을 키우며\\n미래를 향해 나아갈 수 있도록 지원합니다.\"\\n\\n2024년 재단법인 손태희장학재단 장학생 선발계획을 다음과 같이 공고합니다.\\n2024년 8월 1일\\n재단법인 손태희장학재단 이사장 김\\n\\n[3000 0203\\n\\n  장학생 선발인원 및 장학금\\n\\n \\n\\n \\n\\n \\n\\n※ 잠학금은 성적우수와 학샘장러로 지원유형이 구분되어 있으며, 학생들은 자신의\\n필요에 따라 등록금성과 생활비성 중 하나를 선택할 수 있음\\n(중복지원은 불가능함.)\\n\\x0c', '  장학생 지원 자격\\n\\n< 공롱자격 >\\n\\n0\\n\\n* 대학생: 4년제 대학교 직전 학기 12확:\\n\\n(100점 만점) 이상인 학생\\n\\n※ <멀지 제1초> 대학교 재학생 성적 산출 방법 참고 ※\\n\\n성적 우수 장학글\\n\\n 대학생\\n\\n점) 이상인 학생\\n\\nF\\n\\na\\n\\nRO\\n\\nㅠ 직전 학기 12학\\n\\n}금\\n\\n2\\n\\n \\n\\n이 있는 확생\\n\\n때 장하성 선발점차\\n\\n \\n\\n고\\n+\\na   해\\n\\n \\n\\n \\n\\n \\n\\n \\n\\nma 자\\n※\\n\\n머\\n& lk\\n\\n \\n\\n \\n\\n \\n\\nx\\n\\n \\n\\n \\n\\n의 제출 서\\n\\n추천된 지원자\\n제기할 수 없음\\n짐학재단 춤페이지에 게시되며,\\n\\n하며\\n\\n준에 의거\\n\\n로 공정하게 선발되며, 이에 따른 결과에 이의\\n\\n=\\n0]\\n\\n한하며 문자\\n\\n함격자메\\n\\n(재)손태희\\n\\n이메일로\\n\\n41\\n때\\n\\naw\\nwy\\n\\nHo\\nim\\n\\nWo\\n\\n해\\n\\n메시지\\n\\x0c', \"El 224 se 인정\\n\\n비고\\n\\n \\n\\nSHO) FA\\n\\n(sontaehee .co.kr)\\n\\n \\n\\nag      추진\\n\\n8/1(목)     모집   - 전국 대학:\\n\\n~ 9/1(일)           - 공고문 잠'\\n\\n8/26(될)\\n\\n~9/2(2)    접수   - 장학생 서\\n16시\\n\\n등기무편 접수)\\n\\n \\n\\n9/5(목)    선정위원회\\n\\n \\n\\n \\n\\n \\n\\n-9/18(3) | - 침사      때\\n장학생                               동보 및\\na          - 장학생 선정 대싱\\n1078(화) ㅣ 시 고기 | 정합성 선정 대상자               페이지 공고\\n장학증서  이 나서\\n11될 ~ 12될   수여식\\n예정     ae\\n장학금\\n_ 장학금 지\\n‘ls     장학\\n\\n \\n\\n \\n\\n※선발 일정은 재단 내부 사정에 따라 조정 및 변경 될 수 있몸.\\n\\n \\n\\x0c\"]"
    },
    {
        "title": "2024학년도 2학기 국가근로장학금 (2차) 신청 안내(8. 14. 9시 ~ 9. 11. 18시)",
        "url": "https://www.jj.ac.kr/jj/community/notice/janghaknotice.jsp?mode=view&article_no=438018&amp;board_wrapper=%2Fjj%2Fcommunity%2Fnotice%2Fjanghaknotice.jsp&amp;pager.offset=40&amp;board_no=1077",
        "content": "<2024학년도 2학기 국가근로장학금 (2차) 신청 안내>\n2024학년도 2학기 국가근로장학금(2차) 학생 신청기간 및 신청 방법을 안내해드립니다.\nㅇ 국가근로장학금이란?: 지정된 근로지에서 근로하고 그에 따른 장학금을 월별 수혜\nㅇ 신청 대상:\n- 동계방학집중근로(2025년 1월~2월) 활동 희망자로,\n※ 금번 국가근로 2차 신청자는 학기중 국가근로(2024년 9월~) 참여는 불가\n합니다.\n- 우리 대학 정규학기 재학생 중 직전학기(2024-1) 백분위 성적이 70점 이상이며,\n- 당해학기(2024-2) 학자금지원구간(소득분위) 9분위 이하인 학생\n* 근로장학사업 간의(국가근로 학기중, 보람근로, 대학생 청소년교육지원사업 등) 중복 참여 불가\nㅇ 신청 기간: 2024. 8. 14.(수) 09:00 ~ 9. 11.(수) 18:00\n(서류제출 및 가구원동의 기간: 2024. 8. 14.(수) 09:00 ~ 9. 19.(목) 18시\nㅇ 신청 방법: 한국장학재단 홈페이지 또는 모바일 앱(붙임문서 참고)\nㅇ근로 내용:\n- 동계방학집중근로 기간: 2025년 1월~2월 중\n- 근로지: 전국 교외 기관으로 주로 (준)공공기관(★ 교내 근로지는 미운영)\n- 시급: 12,220원(최대 근로시간은 300시간 내외로 변동 가능하며, 정확한 근로 기간 및 최대 근로 가능 시간은 추후 안내)\n- 동계방학집중근로 희망근로지 신청 필수(희망근로지 신청을 해야 신청이 최종적으로 완료됨): 2024년 10월~11월 중\n* 희망근로지 신청 기간은 한국장학재단에서 지정하며, 추후 학교 홈페이지 공지 예정\nㅇ문의\n- 한국장학재단 홈페이지, 모바일 어플 시스템 오류 등 문의 사항 1599-2290\n- 학생지원실 063-220-2162,2172 ['이미지 없음']"
    },
    {
        "title": "(서울 시민/자녀) 2024년 서울희망 대학 진로 장학금 장학생 선발 공고(7. 23. 10시~7. 30. 16시)",
        "url": "https://www.jj.ac.kr/jj/community/notice/janghaknotice.jsp?mode=view&article_no=437519&amp;board_wrapper=%2Fjj%2Fcommunity%2Fnotice%2Fjanghaknotice.jsp&amp;pager.offset=40&amp;board_no=1077",
        "content": "자세한 사항 붙임 파일 참고 ['재단\\n\\n서울장확재단 공고 제2024-15호\\n2024년 <서울희망 대학 진로 장학금> 장학생 선발공고\\n\\n<서울희망 다학 진로 장학금>은 대학생들의 진로활동과 학업에 매진할 수 있는 기회를 제\\n공하여 학엽의 성취도 향상 및 진로, 취업활동에 경쟁력을 높여 건강한 미래 인재로 성장하\\n도록 지원합니다.\\n\\n2024년 7월 12일\\n(재)서울장학재단 이사장\\nEy #23 712\\n1. 사 업 명: 서울희망 대학 진로 장학금\\n2. 지원대상: 서울 소재 대학교 재학생 또는 서울 시민(의 자녀)이면서 비서물 소재 대학교\\n2024년 1학기 재학 후 2학기 정규학기 재학생(예짱으로서 기초생활수급자\\n법정차상우계충. 2024년 1학기 또는 2학기 학자금 지원 4구간 이하인 자\\n\\n원: 진로탐색분야 - 607명 / 학업취업분야 - 406명)\\n\\x0c', '6. 지원기간: 2024년(2회 분할 지급)\\n\\n7. 선발절차\\n신청서 접수         1차 심사\\n온라인 신청 사무국 심사\\n\\n2차 심사\\n\\n서류심사\\n\\n3차 심사\\n\\n장학생\\n선정위원회\\n\\x0c']"
    },
    {
        "title": "정읍시민장학재단 장학생(우수인재 장학금) 선발 7/15~7/24",
        "url": "https://www.jj.ac.kr/jj/community/notice/janghaknotice.jsp?mode=view&article_no=437354&amp;board_wrapper=%2Fjj%2Fcommunity%2Fnotice%2Fjanghaknotice.jsp&amp;pager.offset=40&amp;board_no=1077",
        "content": "['. 』선발개요\\nㅇ 선받인원\\n\\n- 고등학생 : 20명(\\n- 전 문 대 : 16명(\\n- 4 년 대 : 88명(\\nㅇ 장학금4 지급액\\n\\n \\n  \\n\\nI\\n=\\nN\\na\\nof\\n고\\ntito\\n\\n27명, 기타 35명)\\n\\n… 236,400천원\\n- 고등학생 :  700,000원 × 209 = 14.000천원\\n\\n- 전 문 대 : 1,800,0008 x 169 = 28,800천원\\n\\n-4 Wd: 2,200,0008 x  88명\\n\\n193,600천원\\n\\x0c', '、 』 자격기준\\nSHINE\\n\\n \\n\\n \\n\\n \\n\\n \\n\\nㅣ\\n자녀로 관내 고등학교 재학생이거나 관내:외 대학교 재\\n※ 단, 기혼자와 부모           본\\n성적기준\\nㅇ 고등학생\\n- 1학년 : 당해연도 1학기 이수한 전과목 평점평균이 85점이상인 자\\nㅇ 대학생\\n- 신입생 : 당해연도 1학기 평점평균이 (백분위 환산)85점 이상인 자\\n- 재학생 : 2019년 2학기와 2020년 1학기 평점평균이 (백분위 환산)\\n85점 이상인 자\\n 학년제 성적을 산출하는 대학 재학생의 경우에 한하여,\\n2019학년도 1년 성적을 기준으로 평가\\n\\n \\n\\n \\n\\n \\n\\n \\n\\n- 학기별(전년도 3하기, 당해연도 1하기) 최소 9학점 이상 이수한 자\\n> 복학생 및 편입생의 경우 : 당해연도 1학기 성적 적용\\n- 정기학기의 성적 및 학점 기준으로 하며 계절학기는 제외\\nㅇ 기타 이사회에서 특별히 인정하는 자\\n- 예체능 특기자 : 공고일로부터 1년 이내로 전국대회 3위이내,\\n로내대회 1위 입상자이며 전체인원의 10100을\\n초과하지 못함\\n\\n- 우수대학 또는 우수학과 재학생으로 전체인원의 20/100을 넘지 않음\\n\\nwr\\n\\x0c', ', 지원서 접수\\nㅇ 접수기간 : 2020. 8. 21(금) ~ 8. 28(금) 18:00한(주말-공휴일제외)\\nㅇ 접 수 처 : 주민등록지 읍편동사무소 (방문 제출)\\n\\n※ 예체능 특기자의 경우 시청 교육체육청소년과 직접 접수\\nㅇ 구비서류\\n\\n1. 정읍시민장학재단 장학생지원서 1부 [서식 1】\\n\\n2. 성적 등 확인서류 (성적증명서)\\n\\n3. ANAS 확인할 수 있는 서류\\n납부확인서 (2019. 7. 1 ~ 2020. 6. 30)\\n헐료를 납부하는 경우\\n)보험납부확인서 각각 모두 제출 (맞벌이 부부 등)\\n3       부하는 경우\\n카는 1명은 건강보험료 납부확인서,\\n\\n은 자격득실 확인서를 케출\\n\\n는\\n\\n=\\nAL\\nws\\nq wa\\nwn\\n+n\\n\\na\\n7\\na\\nS !\\nbe\\n\\n년\\n시\\n\\nHow Hote\\na\\n63\\n\\nXY\\noff\\nmm 으\\nci\\n뚜\\na\\not\\nfa\\nTa,\\nFr\\nel\\noh\\n\\n~\\nke\\n때\\nof,\\nqu A\\n에\\n\\n1\\n\\na 2 a 2\\n\\nrm\\nnu\\n&\\nae\\n1\\nfe oof 기\\nr\\n\\n2\\n4u\\nfa\\na\\nfi\\nAr\\nSs\\n\\n모의 건장보험료를 납부하고 있는 부양자의 건장보험 남부 확인서와\\n\\n4) 신청인 본인의 소득이 있는 경우와 신청인이 기혼자의 경우\\n~ 본인 및 깨우자의 건강보험료남부확인서 또는 자격득실확인서 제출\\n\\n※ 자격득싶확인서의 경우 2019년 7월 1일 이전부터 현재까지\\n변동사항을 확인 가능하도록 발급-\\n\\x0c', ' \\n\\n \\n\\n5. 주민등록 등본 1부\\n가. 주소지 변동 있는 경우 주소변동사항 포함 발급(거주기간 확인)\\n나. 학생과 부모가 따로 있는 경우 가족관계증명서(부모 기준)제출\\n\\n6. 개인정보게공활용동의서 1부 [서식 2]\\n\\n7. 특기자의 경우 증빙자료 1부 (공고일로부터 1년 이내 입상자)\\n8. 학적부 vai  및 편입생에 한할)\\n\\n9. 가산점 관련 증빙서류(해당자에 한함)\\n\\n가. 가족관계증명서   1부(3 oe 이상, 한부모 등)\\n나. 소년소녀가장 증명서 1\\n다. 장애인 증명서 ra, 본인만 적용 / 3급 이내)\\n라. 국가보훈대상자 증명서 1부\\n※ 국가보훈기본법에 의하여 국가 보훈내상자 자녀로 지정된 경우만 해당\\n\\x0c']"
    },
    {
        "title": "2024년 2학기 한국장학재단 푸른등대 기부장학금 신청 안내(7. 10. 9시~7. 25. 18시)",
        "url": "https://www.jj.ac.kr/jj/community/notice/janghaknotice.jsp?mode=view&article_no=437234&amp;board_wrapper=%2Fjj%2Fcommunity%2Fnotice%2Fjanghaknotice.jsp&amp;pager.offset=40&amp;board_no=1077",
        "content": "자세한 사항 붙임 파일 참고 ['이미지 없음']"
    },
    {
        "title": "2025학년도 소아 청소년 당뇨인 푸른빛 희망 장학금 지원사업 안내(~9. 19.)",
        "url": "https://www.jj.ac.kr/jj/community/notice/janghaknotice.jsp?mode=view&article_no=437218&amp;board_wrapper=%2Fjj%2Fcommunity%2Fnotice%2Fjanghaknotice.jsp&amp;pager.offset=40&amp;board_no=1077",
        "content": "자세한 사항 붙임 참고 ['이미지 없음']"
    }
]